Workbook

Sheet Allocation
A3: Sum of Confirmed Quantity (CS) | B3: Column Labels
A4: Row Labels | B4: 2910 | C4: 2920 | D4: 2925 | E4: 2930 | F4: (blank) | G4: Grand Total | H4: Unique Key
A5: 10001127 | B5: 0 | G5: 0 | H5: =A5 & "_" & 2910 -> 10001127_2910
A6: 10003061 | E6: 0 | G6: 0 | H6: =A6 & "_" & 2910 -> 10003061_2910
A7: 10007757 | B7: 0 | G7: 0 | H7: =A7 & "_" & 2910 -> 10007757_2910
A8: 10007843 | B8: 0 | C8: 8 | G8: 8 | H8: =A8 & "_" & 2910 -> 10007843_2910
A9: 10007849 | C9: 1 | G9: 1 | H9: =A9 & "_" & 2910 -> 10007849_2910
A10: 10007851 | C10: 74 | G10: 74 | H10: =A10 & "_" & 2910 -> 10007851_2910
A11: 10010749 | E11: 0 | G11: 0 | H11: =A11 & "_" & 2910 -> 10010749_2910
A12: 10010755 | B12: 0 | E12: 0 | G12: 0 | H12: =A12 & "_" & 2910 -> 10010755_2910
A13: 10011275 | E13: 0 | G13: 0 | H13: =A13 & "_" & 2910 -> 10011275_2910
A14: 10013039 | C14: 0 | E14: 2 | G14: 2 | H14: =A14 & "_" & 2910 -> 10013039_2910
A15: 10013105 | C15: 0 | E15: 0 | G15: 0 | H15: =A15 & "_" & 2910 -> 10013105_2910
A16: 10013128 | B16: 0 | G16: 0 | H16: =A16 & "_" & 2910 -> 10013128_2910
A17: 10013144 | B17: 0 | E17: 0 | G17: 0 | H17: =A17 & "_" & 2910 -> 10013144_2910
A18: 10016044 | B18: 0 | G18: 0 | H18: =A18 & "_" & 2910 -> 10016044_2910
A19: 10016081 | B19: 0 | E19: 0 | G19: 0 | H19: =A19 & "_" & 2910 -> 10016081_2910
A20: 10016204 | B20: 0 | C20: 0 | G20: 0 | H20: =A20 & "_" & 2910 -> 10016204_2910
A21: 10016401 | B21: 0 | G21: 0 | H21: =A21 & "_" & 2910 -> 10016401_2910
A22: 10016404 | E22: 0 | G22: 0 | H22: =A22 & "_" & 2910 -> 10016404_2910
A23: 10016408 | B23: 0 | G23: 0 | H23: =A23 & "_" & 2910 -> 10016408_2910
A24: 10017114 | E24: 0 | G24: 0 | H24: =A24 & "_" & 2910 -> 10017114_2910
A25: 10017604 | E25: 0 | G25: 0 | H25: =A25 & "_" & 2910 -> 10017604_2910
A26: 10017611 | B26: 0 | G26: 0 | H26: =A26 & "_" & 2910 -> 10017611_2910
A27: 10017617 | C27: 38 | G27: 38 | H27: =A27 & "_" & 2910 -> 10017617_2910
A28: 10018016 | B28: 0 | G28: 0 | H28: =A28 & "_" & 2910 -> 10018016_2910
A29: 10018053 | B29: 0 | G29: 0 | H29: =A29 & "_" & 2910 -> 10018053_2910
A30: 10018646 | B30: 0 | G30: 0 | H30: =A30 & "_" & 2910 -> 10018646_2910
A31: 10018656 | C31: 0 | G31: 0 | H31: =A31 & "_" & 2910 -> 10018656_2910
A32: 10018657 | B32: 0 | G32: 0 | H32: =A32 & "_" & 2910 -> 10018657_2910
A33: 10018659 | C33: 0 | E33: 0 | G33: 0 | H33: =A33 & "_" & 2910 -> 10018659_2910
A34: 10018661 | B34: 0 | G34: 0 | H34: =A34 & "_" & 2910 -> 10018661_2910
A35: 10018980 | B35: 0 | G35: 0 | H35: =A35 & "_" & 2910 -> 10018980_2910
A36: 10019107 | E36: 0 | G36: 0 | H36: =A36 & "_" & 2910 -> 10019107_2910
A37: 10019131 | B37: 0 | G37: 0 | H37: =A37 & "_" & 2910 -> 10019131_2910
A38: 10019641 | B38: 0 | C38: 0 | G38: 0 | H38: =A38 & "_" & 2910 -> 10019641_2910
A39: 10019648 | B39: 0 | G39: 0 | H39: =A39 & "_" & 2910 -> 10019648_2910
A40: 10019690 | B40: 0 | G40: 0 | H40: =A40 & "_" & 2910 -> 10019690_2910
A41: 10019703 | B41: 0 | E41: 0 | G41: 0 | H41: =A41 & "_" & 2910 -> 10019703_2910
A42: 10019704 | B42: 0 | C42: 0 | G42: 0 | H42: =A42 & "_" & 2910 -> 10019704_2910
A43: 10019706 | B43: 0 | E43: 0 | G43: 0 | H43: =A43 & "_" & 2910 -> 10019706_2910
A44: 10019707 | B44: 0 | E44: 0 | G44: 0 | H44: =A44 & "_" & 2910 -> 10019707_2910
A45: 10019778 | B45: 0 | G45: 0 | H45: =A45 & "_" & 2910 -> 10019778_2910
A46: 10019780 | B46: 0 | G46: 0 | H46: =A46 & "_" & 2910 -> 10019780_2910
A47: 10020850 | E47: 0 | G47: 0 | H47: =A47 & "_" & 2910 -> 10020850_2910
A48: 10020851 | B48: 0 | C48: 0 | E48: 0 | G48: 0 | H48: =A48 & "_" & 2910 -> 10020851_2910
A49: 10023481 | B49: 0 | G49: 0 | H49: =A49 & "_" & 2910 -> 10023481_2910
A50: 10023483 | B50: 0 | E50: 0 | G50: 0 | H50: =A50 & "_" & 2910 -> 10023483_2910
A51: 10029943 | B51: 0 | G51: 0 | H51: =A51 & "_" & 2910 -> 10029943_2910
A52: 10029944 | B52: 0 | G52: 0 | H52: =A52 & "_" & 2910 -> 10029944_2910
A53: 10031164 | C53: 6 | G53: 6 | H53: =A53 & "_" & 2910 -> 10031164_2910
A54: 10033021 | B54: 0 | C54: 0 | G54: 0 | H54: =A54 & "_" & 2910 -> 10033021_2910
A55: 10033115 | E55: 0 | G55: 0 | H55: =A55 & "_" & 2910 -> 10033115_2910
A56: 10033175 | C56: 0 | G56: 0 | H56: =A56 & "_" & 2910 -> 10033175_2910
A57: 10038126 | E57: 0 | G57: 0 | H57: =A57 & "_" & 2910 -> 10038126_2910
A58: 10038130 | E58: 0 | G58: 0 | H58: =A58 & "_" & 2910 -> 10038130_2910
A59: 10038132 | E59: 0 | G59: 0 | H59: =A59 & "_" & 2910 -> 10038132_2910
A60: 10038139 | B60: 0 | G60: 0 | H60: =A60 & "_" & 2910 -> 10038139_2910
A61: 10038153 | E61: 0 | G61: 0 | H61: =A61 & "_" & 2910 -> 10038153_2910
A62: 10040122 | B62: 0 | G62: 0 | H62: =A62 & "_" & 2910 -> 10040122_2910
A63: 10040391 | B63: 0 | G63: 0 | H63: =A63 & "_" & 2910 -> 10040391_2910
A64: 10040699 | C64: 23 | G64: 23 | H64: =A64 & "_" & 2910 -> 10040699_2910
A65: 10040869 | B65: 0 | G65: 0 | H65: =A65 & "_" & 2910 -> 10040869_2910
A66: 10041270 | B66: 0 | G66: 0 | H66: =A66 & "_" & 2910 -> 10041270_2910
A67: 10041273 | B67: 0 | G67: 0 | H67: =A67 & "_" & 2910 -> 10041273_2910
A68: 10042157 | C68: 0 | G68: 0 | H68: =A68 & "_" & 2910 -> 10042157_2910
A69: 10045483 | B69: 0 | G69: 0 | H69: =A69 & "_" & 2910 -> 10045483_2910
A70: 10045485 | E70: 0 | G70: 0 | H70: =A70 & "_" & 2910 -> 10045485_2910
A71: 10049305 | B71: 0 | C71: 81 | E71: 0 | G71: 81 | H71: =A71 & "_" & 2910 -> 10049305_2910
A72: 10050324 | C72: 10 | E72: 0 | G72: 10 | H72: =A72 & "_" & 2910 -> 10050324_2910
A73: 10050485 | C73: 48 | G73: 48 | H73: =A73 & "_" & 2910 -> 10050485_2910
A74: 10050486 | C74: 21 | E74: 0 | G74: 21 | H74: =A74 & "_" & 2910 -> 10050486_2910
A75: 10050609 | E75: 99 | G75: 99 | H75: =A75 & "_" & 2910 -> 10050609_2910
A76: 10050613 | B76: 0 | G76: 0 | H76: =A76 & "_" & 2910 -> 10050613_2910
A77: 10050619 | B77: 0 | G77: 0 | H77: =A77 & "_" & 2910 -> 10050619_2910
A78: 10052076 | B78: 0 | C78: 53 | E78: 0 | G78: 53 | H78: =A78 & "_" & 2910 -> 10052076_2910
A79: 10052110 | B79: 0 | E79: 0 | G79: 0 | H79: =A79 & "_" & 2910 -> 10052110_2910
A80: 10052112 | B80: 0 | G80: 0 | H80: =A80 & "_" & 2910 -> 10052112_2910
A81: 10052114 | B81: 0 | C81: 0 | E81: 0 | G81: 0 | H81: =A81 & "_" & 2910 -> 10052114_2910
A82: 10054147 | B82: 0 | G82: 0 | H82: =A82 & "_" & 2910 -> 10054147_2910
A83: 10057233 | C83: 92 | G83: 92 | H83: =A83 & "_" & 2910 -> 10057233_2910
A84: 10058342 | B84: 0 | C84: 0 | G84: 0 | H84: =A84 & "_" & 2910 -> 10058342_2910
A85: 10058821 | B85: 0 | E85: 0 | G85: 0 | H85: =A85 & "_" & 2910 -> 10058821_2910
A86: 10061008 | B86: 0 | G86: 0 | H86: =A86 & "_" & 2910 -> 10061008_2910
A87: 10061010 | B87: 0 | E87: 0 | G87: 0 | H87: =A87 & "_" & 2910 -> 10061010_2910
A88: 10061013 | B88: 0 | G88: 0 | H88: =A88 & "_" & 2910 -> 10061013_2910
A89: 10061060 | B89: 0 | G89: 0 | H89: =A89 & "_" & 2910 -> 10061060_2910
A90: 10061099 | B90: 0 | G90: 0 | H90: =A90 & "_" & 2910 -> 10061099_2910
A91: 10063101 | B91: 0 | G91: 0 | H91: =A91 & "_" & 2910 -> 10063101_2910
A92: 10063102 | C92: 39 | E92: 0 | G92: 39 | H92: =A92 & "_" & 2910 -> 10063102_2910
A93: 10063103 | C93: 0 | E93: 0 | G93: 0 | H93: =A93 & "_" & 2910 -> 10063103_2910
A94: 10065013 | C94: 0 | E94: 0 | G94: 0 | H94: =A94 & "_" & 2910 -> 10065013_2910
A95: 10066215 | E95: 0 | G95: 0 | H95: =A95 & "_" & 2910 -> 10066215_2910
A96: 10066216 | B96: 0 | G96: 0 | H96: =A96 & "_" & 2910 -> 10066216_2910
A97: 10066217 | E97: 0 | G97: 0 | H97: =A97 & "_" & 2910 -> 10066217_2910
A98: 10067042 | B98: 0 | G98: 0 | H98: =A98 & "_" & 2910 -> 10067042_2910
A99: 10076520 | C99: 122 | E99: 0 | G99: 122 | H99: =A99 & "_" & 2910 -> 10076520_2910
A100: 10076532 | C100: 3 | G100: 3 | H100: =A100 & "_" & 2910 -> 10076532_2910
A101: 10076782 | B101: 0 | C101: 20 | G101: 20 | H101: =A101 & "_" & 2910 -> 10076782_2910
A102: 10076880 | B102: 70 | G102: 70 | H102: =A102 & "_" & 2910 -> 10076880_2910
...

Sheet Overstock
A1: Sales Order | B1: Sales Order Item | C1: Key Account # | D1: Sales Order Type | E1: Creation Date | F1: Order Status | G1: Rejection Status | H1: Sold To Party | I1: Ship To Party | J1: Material | K1: Material Description | L1: Order Quantity (CS) | M1: Confirmed Quantity (CS) | N1: Picked Quantity (CS) | O1: Invoice Quantity (CS) | P1: Invoice # | Q1: Outbound Delivery # | R1: Confirmed Quantity (KG) | S1: Invoice Item Amount | T1: Invoice Quantity (KG) | U1: Item Net Amount | V1: Item Net Amount (Confirmed) | W1: Order Quantity | X1: Order Quantity (KG) | Y1: Picked Quantity (KG) | Z1: Plant | AA1: Ship To Name | AB1: BBD / Shelf Life | AC1: Item Value | AD1: Requested Delivery Date | AE1: Ship to Arrive Date
A2: 3002794 | B2: 20 | C2: ONIND | D2: ZORA | E2: 45790 | F2: C | G2: A | H2: 10214530 | I2: 20214530 | J2: 10018980 | K2: DC CLOTTED CREAM 12X170G | L2: 2 | M2: 0 | N2: 0 | O2: 0 | R2: 0 | S2: 0 | T2: 0 | U2: 60 | V2: 0 | W2: 2 | X2: 0 | Y2: 0 | Z2: 2910 | AA2: NIAGARA HOME BAKERY | AC2: 95.6 | AD2: 45791
A3: 3008049 | B3: 20 | C3: ONIND | D3: ZORA | E3: 45814 | F3: C | G3: A | H3: 10117761 | I3: 20117761 | J3: 10019778 | K3: SNO AMBER MIST 6X200G | L3: 50 | M3: 0 | N3: 0 | O3: 0 | R3: 0 | S3: 0 | T3: 0 | U3: 1000 | V3: 0 | W3: 50 | X3: 0 | Y3: 0 | Z3: 2910 | AA3: MENDEL'S GLOBAL CHEESE (ONLY) | AC3: 917.5 | AD3: 45820
A4: 3008050 | B4: 20 | C4: ONIND | D4: ZORA | E4: 45814 | F4: C | G4: A | H4: 10117598 | I4: 20117598 | J4: 10019778 | K4: SNO AMBER MIST 6X200G | L4: 5 | M4: 0 | N4: 0 | O4: 0 | R4: 0 | S4: 0 | T4: 0 | U4: 100 | V4: 0 | W4: 5 | X4: 0 | Y4: 0 | Z4: 2910 | AA4: FOOD DEPOT INT INC (WHOLESALE) | AC4: 91.75 | AD4: 45820
A5: 3008307 | B5: 30 | C5: ONIND | D5: ZORA | E5: 45817 | F5: C | G5: A | H5: 10717283 | I5: 20717283 | J5: 10019778 | K5: SNO AMBER MIST 6X200G | L5: 3 | M5: 0 | N5: 0 | O5: 0 | R5: 0 | S5: 0 | T5: 0 | U5: 60 | V5: 0 | W5: 3 | X5: 0 | Y5: 0 | Z5: 2910 | AA5: LA BOTTEGA (CHEESE) | AC5: 55.05 | AD5: 45819
A6: 3009475 | B6: 220 | C6: BCIND | D6: ZORA | E6: 45821 | F6: C | G6: A | H6: 10066089 | I6: 20066089 | J6: 10018659 | K6: SOH PRETZELS MINI | L6: 1 | M6: 0 | N6: 0 | O6: 0 | R6: 0 | S6: 0 | T6: 0 | U6: 18.9 | V6: 0 | W6: 1 | X6: 0 | Y6: 0 | Z6: 2930 | AA6: SUNRISE MARKET CLEAROUT | AC6: 27.41 | AD6: 45824
A7: 3010042 | B7: 30 | C7: LIQID | D7: ZORA | E7: 45825 | F7: C | G7: A | H7: 10000912 | I7: 20000912 | J7: 10052114 | K7: STW 170G FIRM APPNZLR STYL | L7: 41 | M7: 0 | N7: 0 | O7: 0 | R7: 0 | S7: 0 | T7: 0 | U7: 41 | V7: 0 | W7: 41 | X7: 0 | Y7: 0 | Z7: 2920 | AA7: NUTRI-GLOBE-P/U FROM CALGARY W/H | AC7: 3019.65 | AD7: 45826
A8: 3010875 | B8: 20 | C8: FSIND | D8: ZORA | E8: 45828 | F8: C | G8: A | H8: 10074880 | I8: 20074880 | J8: 10019778 | K8: SNO AMBER MIST 6X200G | L8: 30 | M8: 0 | N8: 0 | O8: 0 | R8: 0 | S8: 0 | T8: 0 | U8: 510 | V8: 0 | W8: 30 | X8: 0 | Y8: 0 | Z8: 2910 | AA8: WORLDWIDE SPECIALTY FOODS LTD | AC8: 550.5 | AD8: 45833
A9: 3011082 | B9: 30 | C9: ATIND | D9: ZORA | E9: 45831 | F9: C | G9: A | H9: 10000813 | I9: 20000813 | J9: 10018053 | K9: IRELAND MATURE CHED BULK 2X2.5KG | L9: 8 | M9: 0 | N9: 0 | O9: 0 | R9: 0 | S9: 0 | T9: 0 | U9: 448.4 | V9: 0 | W9: 8 | X9: 40 | Y9: 0 | Z9: 2910 | AA9: DOLMA FOOD | AC9: 524.8 | AD9: 45835
A10: 3011635 | B10: 20 | C10: ATIND | D10: ZORA | E10: 45833 | G10: A | H10: 10120116 | I10: 20120116 | J10: 10019778 | K10: SNO AMBER MIST 6X200G | L10: 30 | M10: 0 | N10: 0 | O10: 0 | R10: 0 | S10: 0 | T10: 0 | U10: 510 | V10: 0 | W10: 30 | X10: 0 | Y10: 0 | Z10: 2910 | AA10: MULDER MEATS (1983) LTD | AC10: 550.5 | AD10: 45838
A11: 3011635 | B11: 70 | C11: ATIND | D11: ZORA | E11: 45833 | G11: A | H11: 10120116 | I11: 20120116 | J11: 10018053 | K11: IRELAND MATURE CHED BULK 2X2.5KG | L11: 10 | M11: 0 | N11: 0 | O11: 0 | R11: 0 | S11: 0 | T11: 0 | U11: 560.5 | V11: 0 | W11: 10 | X11: 50 | Y11: 0 | Z11: 2910 | AA11: MULDER MEATS (1983) LTD | AC11: 656 | AD11: 45838
A12: 3013228 | B12: 40 | C12: ONIND | D12: ZORA | E12: 45840 | F12: C | G12: A | H12: 10120219 | I12: 20120219 | J12: 10019778 | K12: SNO AMBER MIST 6X200G | L12: 2 | M12: 0 | N12: 0 | O12: 0 | R12: 0 | S12: 0 | T12: 0 | U12: 32 | V12: 0 | W12: 2 | X12: 0 | Y12: 0 | Z12: 2910 | AA12: THE MILL STREET CHEESE MARKET | AC12: 36.7 | AD12: 45842
A13: 3015332 | B13: 10 | C13: BCIND | D13: ZORA | E13: 45849 | F13: C | G13: A | H13: 10049999 | I13: 20049999 | J13: 10061010 | K13: BEL BOUR 150G GARLIC & HERB | L13: 51 | M13: 0 | N13: 0 | O13: 0 | R13: 0 | S13: 0 | T13: 0 | U13: 459 | V13: 0 | W13: 51 | X13: 0 | Y13: 0 | Z13: 2930 | AA13: OLD COUNTRY MKT ALBERNI DELI | AC13: 2557.65 | AD13: 45850
A14: 3015332 | B14: 100 | C14: BCIND | D14: ZORA | E14: 45849 | F14: C | G14: A | H14: 10049999 | I14: 20049999 | J14: 10016081 | K14: CLAWSON HUNTSMN 5 LAY BULK 2X2KG | L14: 4 | M14: 0 | N14: 0 | O14: 0 | R14: 0 | S14: 0 | T14: 0 | U14: 160 | V14: 0 | W14: 4 | X14: 16 | Y14: 0 | Z14: 2930 | AA14: OLD COUNTRY MKT ALBERNI DELI | AC14: 362.4 | AD14: 45850
A15: 3016217 | B15: 90 | C15: ONIND | D15: ZORA | E15: 45854 | F15: C | G15: A | H15: 10125105 | I15: 20125105 | J15: 10040122 | K15: BAL SNACKS CHOCO LATTE | L15: 30 | M15: 0 | N15: 0 | O15: 0 | R15: 0 | S15: 0 | T15: 0 | U15: 240 | V15: 0 | W15: 30 | X15: 0 | Y15: 0 | Z15: 2910 | AA15: ELLIOT LAKE MEATS AND DELI | AC15: 842.1 | AD15: 45859
A16: 3019222 | B16: 90 | C16: BCIND | D16: ZORA | E16: 45867 | F16: C | G16: A | H16: 10049999 | I16: 20049999 | J16: 10016081 | K16: CLAWSON HUNTSMN 5 LAY BULK 2X2KG | L16: 7 | M16: 0 | N16: 0 | O16: 0 | R16: 0 | S16: 0 | T16: 0 | U16: 336 | V16: 0 | W16: 7 | X16: 28 | Y16: 0 | Z16: 2930 | AA16: OLD COUNTRY MKT ALBERNI DELI | AC16: 634.2 | AD16: 45870
A17: 3019356 | B17: 100 | C17: LIQID | D17: ZORA | E17: 45868 | F17: C | G17: A | H17: 10150032 | I17: 20150032 | J17: 10019780 | K17: SNO BLACK BOMBER 1X2KG | L17: 9 | M17: 0 | N17: 0 | O17: 0 | R17: 0 | S17: 0 | T17: 0 | U17: 126 | V17: 0 | W17: 9 | X17: 18 | Y17: 0 | Z17: 2910 | AA17: COUNTRY TRADITIONS FROZEN FOODS | AC17: 512.82 | AD17: 45870
A18: 3019356 | B18: 140 | C18: LIQID | D18: ZORA | E18: 45868 | F18: C | G18: A | H18: 10150032 | I18: 20150032 | J18: 10050619 | K18: CB CRUNCHY PEANUT BUTTER | L18: 2 | M18: 0 | N18: 0 | O18: 0 | R18: 0 | S18: 0 | T18: 0 | U18: 12 | V18: 0 | W18: 2 | X18: 0 | Y18: 0 | Z18: 2910 | AA18: COUNTRY TRADITIONS FROZEN FOODS | AC18: 33.52 | AD18: 45870
A19: 3019752 | B19: 230 | C19: BCIND | D19: ZORA | E19: 45869 | F19: C | G19: A | H19: 10062506 | I19: 20062506 | J19: 10010749 | K19: CL GOODA CHEESE SPICED | L19: 3 | M19: 0 | N19: 0 | O19: 0 | R19: 0 | S19: 0 | T19: 0 | U19: 40.5 | V19: 0 | W19: 3 | X19: 13.5 | Y19: 0 | Z19: 2930 | AA19: LO-BOY MARKET CLEARANCE | AC19: 167.27 | AD19: 45874
A20: 3019752 | B20: 260 | C20: BCIND | D20: ZORA | E20: 45869 | F20: C | G20: A | H20: 10062506 | I20: 20062506 | J20: 10066217 | K20: KC SEA SALT 56G GF | L20: 18 | M20: 0 | N20: 0 | O20: 0 | R20: 0 | S20: 0 | T20: 0 | U20: 72 | V20: 0 | W20: 18 | X20: 0 | Y20: 0 | Z20: 2930 | AA20: LO-BOY MARKET CLEARANCE | AC20: 412.56 | AD20: 45874
A21: 3019989 | B21: 180 | C21: LIQID | D21: ZORA | E21: 45870 | F21: C | G21: A | H21: 10225936 | I21: 20225936 | J21: 10016044 | K21: CC CHED W HORSERADISH 12X150G | L21: 20 | M21: 0 | N21: 0 | O21: 0 | R21: 0 | S21: 0 | T21: 0 | U21: 160 | V21: 0 | W21: 20 | X21: 0 | Y21: 0 | Z21: 2910 | AA21: ALMOST PERFECT | AC21: 653.2 | AD21: 45876
A22: 3021494 | B22: 10 | C22: LIQID | D22: ZORA | E22: 45880 | F22: C | G22: A | H22: 10000913 | I22: 20000913 | J22: 10063102 | K22: CAPE CHIPS SALT LS FAT 220G | L22: 4 | M22: 0 | N22: 0 | O22: 0 | R22: 0 | S22: 0 | T22: 0 | U22: 12 | V22: 0 | W22: 4 | X22: 0 | Y22: 0 | Z22: 2930 | AA22: NUTRI-GLOBE-P/U FR SURREY BRANCH | AC22: 149.72 | AD22: 45883
A23: 3022985 | B23: 10 | C23: ONIND | D23: ZORA | E23: 45888 | F23: C | G23: A | H23: 10130665 | I23: 20130665 | J23: 10019780 | K23: SNO BLACK BOMBER 1X2KG | L23: 6 | M23: 0 | N23: 0 | O23: 0 | R23: 0 | S23: 0 | T23: 0 | U23: 228 | V23: 0 | W23: 6 | X23: 12 | Y23: 0 | Z23: 2910 | AA23: SCHEFFLERS MEAT (CHEESE) | AC23: 311.4 | AD23: 45889
... A79: 3056334 | B79: 50 | C79: ONIND | D79: ZORA | E79: 46062 | F79: C | G79: A | H79: 10159306 | I79: 20159306 | J79: 10061010 | K79: BEL BOUR 150G GARLIC & HERB | L79: 116 | M79: 0 | N79: 0 | O79: 0 | R79: 0 | S79: 0 | T79: 0 | U79: 2061.32 | V79: 0 | W79: 116 | X79: 0 | Y79: 0 | Z79: 2910 | AA79: ZARKY'S FINE FOODS | AC79: 5809.28 | AD79: 46064
A80: 3056403 | B80: 30 | C80: ONIND | D80: ZORA | E80: 46062 | G80: A | H80: 10117854 | I80: 20117854 | J80: 10016081 | K80: CLAWSON HUNTSMN 5 LAY BULK 2X2KG | L80: 28 | M80: 0 | N80: 0 | O80: 0 | R80: 0 | S80: 0 | T80: 0 | U80: 1237.6 | V80: 0 | W80: 28 | X80: 112 | Y80: 0 | Z80: 2910 | AA80: MENDEL'S GLOBAL CHEESE (ONLY) | AC80: 2736.16 | AD80: 46064
A81: 3056411 | B81: 70 | C81: ATIND | D81: ZORA | E81: 46062 | F81: C | G81: A | H81: 10780161 | I81: 20780161 | J81: 10061010 | K81: BEL BOUR 150G GARLIC & HERB | L81: 50 | M81: 0 | N81: 0 | O81: 0 | R81: 0 | S81: 0 | T81: 0 | U81: 888.5 | V81: 0 | W81: 50 | X81: 0 | Y81: 0 | Z81: 2910 | AA81: CANNING & CORNWALLIS VALUFOODS | AC81: 2504 | AD81: 46070
A82: 3056435 | B82: 20 | C82: LIQID | D82: ZORA | E82: 46062 | F82: C | G82: A | H82: 10123006 | I82: 21000245 | J82: 10061010 | K82: BEL BOUR 150G GARLIC & HERB | L82: 50 | M82: 0 | N82: 0 | O82: 0 | R82: 0 | S82: 0 | T82: 0 | U82: 888.5 | V82: 0 | W82: 50 | X82: 0 | Y82: 0 | Z82: 2910 | AA82: NUTRI-GLOBE MARKETING | AC82: 2504 | AD82: 46065
A83: 3056492 | B83: 30 | C83: ONIND | D83: ZORA | E83: 46063 | G83: A | H83: 10110520 | I83: 20110520 | J83: 10019703 | K83: OKA CHEESE SWIS SMKD 1X4.5KG | L83: 5 | M83: 0 | N83: 0 | O83: 0 | R83: 0 | S83: 0 | T83: 0 | U83: 167.18 | V83: 0 | W83: 5 | X83: 22.5 | Y83: 0 | Z83: 2910 | AA83: LADY YORK | AC83: 486.68 | AD83: 46065
A84: 3056492 | B84: 40 | C84: ONIND | D84: ZORA | E84: 46063 | G84: A | H84: 10110520 | I84: 20110520 | J84: 10016081 | K84: CLAWSON HUNTSMN 5 LAY BULK 2X2KG | L84: 28 | M84: 0 | N84: 0 | O84: 0 | R84: 0 | S84: 0 | T84: 0 | U84: 1237.6 | V84: 0 | W84: 28 | X84: 112 | Y84: 0 | Z84: 2910 | AA84: LADY YORK | AC84: 2736.16 | AD84: 46065
A85: 3056507 | B85: 20 | C85: ATIND | D85: ZORA | E85: 46063 | F85: C | G85: A | H85: 10125620 | I85: 20125620 | J85: 10016081 | K85: CLAWSON HUNTSMN 5 LAY BULK 2X2KG | L85: 2 | M85: 0 | N85: 0 | O85: 0 | R85: 0 | S85: 0 | T85: 0 | U85: 88.4 | V85: 0 | W85: 2 | X85: 8 | Y85: 0 | Z85: 2910 | AA85: MASSTOWN CREAMERY LTD | AC85: 195.44 | AD85: 46070
A86: 3056525 | B86: 170 | C86: ONIND | D86: ZORA | E86: 46063 | F86: C | G86: A | H86: 10125105 | I86: 20125105 | J86: 10061010 | K86: BEL BOUR 150G GARLIC & HERB | L86: 116 | M86: 0 | N86: 0 | O86: 0 | R86: 0 | S86: 0 | T86: 0 | U86: 2061.32 | V86: 0 | W86: 116 | X86: 0 | Y86: 0 | Z86: 2910 | AA86: ELLIOT LAKE MEATS AND DELI | AC86: 5809.28 | AD86: 46070
A87: 3056729 | B87: 100 | C87: BCIND | D87: ZORA | E87: 46063 | F87: C | G87: A | H87: 10001663 | I87: 20001663 | J87: 10066215 | K87: KC HONEY DIJON 56G GF | L87: 8 | M87: 0 | N87: 0 | O87: 0 | R87: 0 | S87: 0 | T87: 0 | U87: 53.28 | V87: 0 | W87: 8 | X87: 0 | Y87: 0 | Z87: 2930 | AA87: FALCON ESSENTIALS | AC87: 197.84 | AD87: 46066
A88: 3058318 | B88: 160 | C88: LIQID | D88: ZORA | E88: 46071 | F88: C | G88: A | H88: 10123006 | I88: 21000245 | J88: 10061008 | K88: BEL BOUR 150G CRACKD BLK PEP | L88: 28 | M88: 0 | N88: 0 | O88: 0 | R88: 0 | S88: 0 | T88: 0 | U88: 248.92 | V88: 0 | W88: 28 | X88: 0 | Y88: 0 | Z88: 2910 | AA88: NUTRI-GLOBE MARKETING | AC88: 704.76 | AD88: 46073
A89: 3058545 | B89: 40 | C89: ATIND | D89: ZORA | E89: 46072 | F89: C | G89: A | H89: 10125176 | I89: 20125176 | J89: 10019641 | K89: AGROSGN BRIE CHEVALR TC 650G | L89: 2 | M89: 0 | N89: 0 | O89: 0 | R89: 0 | S89: 0 | T89: 0 | U89: 35.41 | V89: 0 | W89: 2 | X89: 5.2 | Y89: 0 | Z89: 2910 | AA89: G&J GROCERY LTD | AC89: 142.58 | AD89: 46077
A90: 3058752 | B90: 200 | C90: BCIND | D90: ZORA | E90: 46073 | F90: C | G90: A | H90: 10062506 | I90: 20062506 | J90: 10033175 | K90: BC 540G OLD CHEDDAR CHEESE | L90: 8 | M90: 0 | N90: 0 | O90: 0 | R90: 0 | S90: 0 | T90: 0 | U90: 160 | V90: 0 | W90: 8 | X90: 0 | Y90: 0 | Z90: 2920 | AA90: LO-BOY MARKET CLEARANCE | AC90: 938.88 | AD90: 46077
A91: 3059050 | B91: 10 | C91: PRIND | D91: ZORA | E91: 46076 | F91: C | G91: A | H91: 13000090 | I91: 21000165 | J91: 10065013 | K91: G.H. POPCORN CARAMEL 227G | L91: 20 | M91: 0 | N91: 0 | O91: 0 | R91: 0 | S91: 0 | T91: 0 | U91: 259.6 | V91: 0 | W91: 20 | X91: 0 | Y91: 0 | Z91: 2920 | AA91: Liquidation Warehouse | AC91: 819 | AD91: 46079
A92: 3059246 | B92: 10 | C92: ATIND | D92: ZORA | E92: 46077 | F92: C | G92: A | H92: 13000158 | I92: 21000254 | J92: 10019703 | K92: OKA CHEESE SWIS SMKD 1X4.5KG | L92: 20 | M92: 0 | N92: 0 | O92: 0 | R92: 0 | S92: 0 | T92: 0 | U92: 668.7 | V92: 0 | W92: 20 | X92: 90 | Y92: 0 | Z92: 2910 | AA92: MULHOUSE FINE FOODS | AC92: 2009.7 | AD92: 46083
A93: 3059261 | B93: 10 | C93: ONIND | D93: ZORA | E93: 46077 | F93: C | G93: A | H93: 10125105 | I93: 20125105 | J93: 10019703 | K93: OKA CHEESE SWIS SMKD 1X4.5KG | L93: 20 | M93: 0 | N93: 0 | O93: 0 | R93: 0 | S93: 0 | T93: 0 | U93: 668.7 | V93: 0 | W93: 20 | X93: 90 | Y93: 0 | Z93: 2910 | AA93: ELLIOT LAKE MEATS AND DELI | AC93: 2009.7 | AD93: 46083
A94: 3059261 | B94: 130 | C94: ONIND | D94: ZORA | E94: 46077 | F94: C | G94: A | H94: 10125105 | I94: 20125105 | J94: 10067042 | K94: KC AIR FRIED TEXAS BBQ GF | L94: 2 | M94: 0 | N94: 0 | O94: 0 | R94: 0 | S94: 0 | T94: 0 | U94: 16 | V94: 0 | W94: 2 | X94: 0 | Y94: 0 | Z94: 2910 | AA94: ELLIOT LAKE MEATS AND DELI | AC94: 56.38 | AD94: 46083
A95: 3059261 | B95: 170 | C95: ONIND | D95: ZORA | E95: 46077 | F95: C | G95: A | H95: 10125105 | I95: 20125105 | J95: 10018646 | K95: SOH PRETZEL PIECE CHEDDAR | L95: 25 | M95: 0 | N95: 0 | O95: 0 | R95: 0 | S95: 0 | T95: 0 | U95: 200 | V95: 0 | W95: 25 | X95: 0 | Y95: 0 | Z95: 2910 | AA95: ELLIOT LAKE MEATS AND DELI | AC95: 666.25 | AD95: 46083
A96: 3059261 | B96: 210 | C96: ONIND | D96: ZORA | E96: 46077 | F96: C | G96: A | H96: 10125105 | I96: 20125105 | J96: 10061013 | K96: BEL BOUR 150GR SHAL & CHIVES | L96: 39 | M96: 0 | N96: 0 | O96: 0 | R96: 0 | S96: 0 | T96: 0 | U96: 346.71 | V96: 0 | W96: 39 | X96: 0 | Y96: 0 | Z96: 2910 | AA96: ELLIOT LAKE MEATS AND DELI | AC96: 959.79 | AD96: 46083
... A256: 3078628 | B256: 20 | C256: ATIND | D256: ZORA | E256: 46175 | F256: C | G256: A | H256: 13000158 | I256: 21000254 | J256: 10100028 | K256: BCC CHEESE BURRATA 6x250G | L256: 4 | M256: 0 | N256: 0 | O256: 0 | R256: 0 | S256: 0 | T256: 0 | U256: 51.2 | V256: 0 | W256: 4 | X256: 0 | Y256: 0 | Z256: 2910 | AA256: MULHOUSE FINE FOODS | AC256: 154.12 | AD256: 46183
A257: 3078694 | B257: 10 | C257: LIQID | D257: ZORA | E257: 46175 | F257: C | G257: A | H257: 13000299 | I257: 21000882 | J257: 10100278 | K257: RED BARON FZ DDS PEPPERONI | L257: 17 | M257: 17 | N257: 17 | O257: 0 | Q257: 80122486 | R257: 0 | S257: 0 | T257: 0 | U257: 142.8 | V257: 142.8 | W257: 17 | X257: 0 | Y257: 0 | Z257: 2925 | AA257: NF Sales Ltd (Liquidation Guy)-CAL FRZ | AB257: 46295 | AC257: 721.14 | AD257: 46177 | AE257: 46177
A258: 3078694 | B258: 20 | C258: LIQID | D258: ZORA | E258: 46175 | F258: C | G258: A | H258: 13000299 | I258: 21000882 | J258: 10100282 | K258: RED BARON FZ FL HT PIZZA MEAT LOVERS | L258: 480 | M258: 480 | N258: 480 | O258: 0 | Q258: 80122486 | R258: 0 | S258: 0 | T258: 0 | U258: 4704 | V258: 4704 | W258: 480 | X258: 0 | Y258: 0 | Z258: 2925 | AA258: NF Sales Ltd (Liquidation Guy)-CAL FRZ | AB258: 46308 | AC258: 46070.4 | AD258: 46177 | AE258: 46177
A259: 3078694 | B259: 30 | C259: LIQID | D259: ZORA | E259: 46175 | F259: C | G259: A | H259: 13000299 | I259: 21000882 | J259: 10100282 | K259: RED BARON FZ FL HT PIZZA MEAT LOVERS | L259: 48 | M259: 48 | N259: 48 | O259: 0 | Q259: 80122486 | R259: 0 | S259: 0 | T259: 0 | U259: 470.4 | V259: 470.4 | W259: 48 | X259: 0 | Y259: 0 | Z259: 2925 | AA259: NF Sales Ltd (Liquidation Guy)-CAL FRZ | AB259: 46296 | AC259: 4607.04 | AD259: 46177 | AE259: 46177
A260: 3078694 | B260: 40 | C260: LIQID | D260: ZORA | E260: 46175 | F260: C | G260: A | H260: 13000299 | I260: 21000882 | J260: 10100282 | K260: RED BARON FZ FL HT PIZZA MEAT LOVERS | L260: 24 | M260: 24 | N260: 24 | O260: 0 | Q260: 80122486 | R260: 0 | S260: 0 | T260: 0 | U260: 235.2 | V260: 235.2 | W260: 24 | X260: 0 | Y260: 0 | Z260: 2925 | AA260: NF Sales Ltd (Liquidation Guy)-CAL FRZ | AB260: 46296 | AC260: 2303.52 | AD260: 46177 | AE260: 46177
A261: 3078694 | B261: 50 | C261: LIQID | D261: ZORA | E261: 46175 | F261: C | G261: A | H261: 13000299 | I261: 21000882 | J261: 10100282 | K261: RED BARON FZ FL HT PIZZA MEAT LOVERS | L261: 6 | M261: 6 | N261: 6 | O261: 0 | Q261: 80122486 | R261: 0 | S261: 0 | T261: 0 | U261: 58.8 | V261: 58.8 | W261: 6 | X261: 0 | Y261: 0 | Z261: 2925 | AA261: NF Sales Ltd (Liquidation Guy)-CAL FRZ | AB261: 46296 | AC261: 575.88 | AD261: 46177 | AE261: 46177
A262: 3078694 | B262: 60 | C262: LIQID | D262: ZORA | E262: 46175 | F262: C | G262: A | H262: 13000299 | I262: 21000882 | J262: 10100282 | K262: RED BARON FZ FL HT PIZZA MEAT LOVERS | L262: 12 | M262: 12 | N262: 12 | O262: 0 | Q262: 80122486 | R262: 0 | S262: 0 | T262: 0 | U262: 117.6 | V262: 117.6 | W262: 12 | X262: 0 | Y262: 0 | Z262: 2925 | AA262: NF Sales Ltd (Liquidation Guy)-CAL FRZ | AB262: 46296 | AC262: 1151.76 | AD262: 46177 | AE262: 46177
A263: 3078700 | B263: 180 | C263: BCIND | D263: ZORA | E263: 46175 | F263: C | G263: A | H263: 10062506 | I263: 21000941 | J263: 10076520 | K263: JW SHORTBREAD FINGERS 115 | L263: 24 | M263: 0 | N263: 0 | O263: 0 | R263: 0 | S263: 0 | T263: 0 | U263: 240 | V263: 0 | W263: 24 | X263: 0 | Y263: 0 | Z263: 2930 | AA263: LO-BOY MARKET CLEARANCE - SURREY DEL | AC263: 1212.72 | AD263: 46177
A264: 3079494 | B264: 10 | C264: LIQID | D264: ZORA | E264: 46178 | F264: C | G264: A | H264: 10123006 | I264: 20000912 | J264: 10042157 | K264: TATES COOKIES OATMEAL RAISIN | L264: 1 | M264: 0 | N264: 0 | O264: 0 | R264: 0 | S264: 0 | T264: 0 | U264: 5 | V264: 0 | W264: 1 | X264: 0 | Y264: 0 | Z264: 2920 | AA264: NUTRI-GLOBE-P/U FROM CALGARY W/H | AC264: 54.95 | AD264: 46183
A265: 3082856 | B265: 30 | C265: LIQID | D265: ZORA | E265: 46195 | F265: C | G265: A | H265: 13000253 | I265: 21000442 | J265: 10029943 | K265: SF PRETZEL CRISP BIT HNY MST | L265: 142 | M265: 0 | N265: 0 | O265: 0 | R265: 0 | S265: 0 | T265: 0 | U265: 1934.04 | V265: 0 | W265: 142 | X265: 0 | Y265: 0 | Z265: 2910 | AA265: Bouffe A Rabais | AC265: 5175.9 | AD265: 46198
A266: 3082863 | B266: 70 | C266: ONIND | D266: ZORA | E266: 46195 | F266: C | G266: A | H266: 10161543 | I266: 20161543 | J266: 10029943 | K266: SF PRETZEL CRISP BIT HNY MST | L266: 20 | M266: 0 | N266: 0 | O266: 0 | R266: 0 | S266: 0 | T266: 0 | U266: 272.4 | V266: 0 | W266: 20 | X266: 0 | Y266: 0 | Z266: 2910 | AA266: SHARPE'S FOOD MARKET | AC266: 729 | AD266: 46197
A267: 3082926 | B267: 30 | C267: ATIND | D267: ZORA | E267: 46195 | F267: C | G267: A | H267: 10120870 | I267: 20120870 | J267: 10016204 | K267: CC 1057 SCOTTISH CHED 12X200G | L267: 25 | M267: 0 | N267: 0 | O267: 0 | R267: 0 | S267: 0 | T267: 0 | U267: 523.5 | V267: 0 | W267: 25 | X267: 0 | Y267: 0 | Z267: 2910 | AA267: MORRIS WHOLESALE LTD | AC267: 1084.25 | AD267: 46197
A268: 3082930 | B268: 10 | C268: ATIND | D268: ZORA | E268: 46195 | F268: C | G268: A | H268: 10780161 | I268: 20780161 | J268: 10016044 | K268: CC CHED W HORSERADISH 12X150G | L268: 10 | M268: 0 | N268: 0 | O268: 0 | R268: 0 | S268: 0 | T268: 0 | U268: 159.6 | V268: 0 | W268: 10 | X268: 0 | Y268: 0 | Z268: 2910 | AA268: CANNING & CORNWALLIS VALUFOODS | AC268: 327.9 | AD268: 46197
A269: 3082930 | B269: 20 | C269: ATIND | D269: ZORA | E269: 46195 | F269: C | G269: A | H269: 10780161 | I269: 20780161 | J269: 10013128 | K269: IL APPLEWOOD SMKD SLICES 8X180G | L269: 20 | M269: 0 | N269: 0 | O269: 0 | R269: 0 | S269: 0 | T269: 0 | U269: 304 | V269: 0 | W269: 20 | X269: 0 | Y269: 0 | Z269: 2910 | AA269: CANNING & CORNWALLIS VALUFOODS | AC269: 597.2 | AD269: 46197
A270: 3082930 | B270: 40 | C270: ATIND | D270: ZORA | E270: 46195 | F270: C | G270: A | H270: 10780161 | I270: 20780161 | J270: 10016204 | K270: CC 1057 SCOTTISH CHED 12X200G | L270: 10 | M270: 0 | N270: 0 | O270: 0 | R270: 0 | S270: 0 | T270: 0 | U270: 209.4 | V270: 0 | W270: 10 | X270: 0 | Y270: 0 | Z270: 2910 | AA270: CANNING & CORNWALLIS VALUFOODS | AC270: 433.7 | AD270: 46197
A271: 3082930 | B271: 50 | C271: ATIND | D271: ZORA | E271: 46195 | F271: C | G271: A | H271: 10780161 | I271: 20780161 | J271: 10029943 | K271: SF PRETZEL CRISP BIT HNY MST | L271: 15 | M271: 0 | N271: 0 | O271: 0 | R271: 0 | S271: 0 | T271: 0 | U271: 204.3 | V271: 0 | W271: 15 | X271: 0 | Y271: 0 | Z271: 2910 | AA271: CANNING & CORNWALLIS VALUFOODS | AC271: 546.75 | AD271: 46197
A272: 3083190 | B272: 190 | C272: BCIND | D272: ZORA | E272: 46196 | F272: C | G272: A | H272: 10062506 | I272: 20062506 | J272: 10016204 | K272: CC 1057 SCOTTISH CHED 12X200G | L272: 5 | M272: 0 | N272: 0 | O272: 0 | R272: 0 | S272: 0 | T272: 0 | U272: 55 | V272: 0 | W272: 5 | X272: 0 | Y272: 0 | Z272: 2920 | AA272: LO-BOY MARKET CLEARANCE | AC272: 222.55 | AD272: 46199
A273: 3083349 | B273: 40 | C273: ATIND | D273: ZORA | E273: 46197 | F273: C | G273: A | H273: 10125176 | I273: 20125176 | J273: 10016204 | K273: CC 1057 SCOTTISH CHED 12X200G | L273: 10 | M273: 0 | N273: 0 | O273: 0 | R273: 0 | S273: 0 | T273: 0 | U273: 209.4 | V273: 0 | W273: 10 | X273: 0 | Y273: 0 | Z273: 2910 | AA273: G&J GROCERY LTD | AC273: 433.9 | AD273: 46202
A274: 3083626 | B274: 60 | C274: LIQID | D274: ZORA | E274: 46198 | F274: C | G274: A | H274: 10150032 | I274: 20150032 | J274: 10016204 | K274: CC 1057 SCOTTISH CHED 12X200G | L274: 100 | M274: 0 | N274: 0 | O274: 0 | R274: 0 | S274: 0 | T274: 0 | U274: 800 | V274: 0 | W274: 100 | X274: 0 | Y274: 0 | Z274: 2910 | AA274: COUNTRY TRADITIONS FROZEN FOODS | AC274: 4339 | AD274: 46199
... A297: 3086073 | B297: 20 | C297: LIQID | D297: ZORA | E297: 46210 | F297: C | G297: A | H297: 10062506 | I297: 21000941 | J297: 10065013 | K297: G.H. POPCORN CARAMEL 227G | L297: 1 | M297: 0 | N297: 0 | O297: 0 | R297: 0 | S297: 0 | T297: 0 | U297: 10 | V297: 0 | W297: 1 | X297: 0 | Y297: 0 | Z297: 2930 | AA297: LO-BOY MARKET CLEARANCE - SURREY DEL | AC297: 42.68 | AD297: 46212
A298: 3086925 | B298: 10 | C298: LIQID | D298: ZORA | E298: 46213 | F298: C | G298: A | H298: 10123006 | I298: 20000912 | J298: 10063102 | K298: CAPE CHIPS SALT LS FAT 220G | L298: 9 | M298: 9 | N298: 9 | O298: 0 | Q298: 80135689 | R298: 0 | S298: 0 | T298: 0 | U298: 27 | V298: 27 | W298: 9 | X298: 0 | Y298: 0 | Z298: 2920 | AA298: NUTRI-GLOBE-P/U FROM CALGARY W/H | AB298: 46214 | AC298: 350.91 | AD298: 46218 | AE298: 46218
A299: 3086925 | B299: 20 | C299: LIQID | D299: ZORA | E299: 46213 | F299: C | G299: A | H299: 10123006 | I299: 20000912 | J299: 10063102 | K299: CAPE CHIPS SALT LS FAT 220G | L299: 30 | M299: 30 | N299: 30 | O299: 0 | Q299: 80135689 | R299: 0 | S299: 0 | T299: 0 | U299: 90 | V299: 90 | W299: 30 | X299: 0 | Y299: 0 | Z299: 2920 | AA299: NUTRI-GLOBE-P/U FROM CALGARY W/H | AB299: 46214 | AC299: 1169.7 | AD299: 46218 | AE299: 46218
A300: 3086925 | B300: 30 | C300: LIQID | D300: ZORA | E300: 46213 | F300: C | G300: A | H300: 10123006 | I300: 20000912 | J300: 10083462 | K300: MCV DIGESTIVE DK CHOC 18592 | L300: 72 | M300: 72 | N300: 72 | O300: 0 | Q300: 80135689 | R300: 0 | S300: 0 | T300: 0 | U300: 216 | V300: 216 | W300: 72 | X300: 0 | Y300: 0 | Z300: 2920 | AA300: NUTRI-GLOBE-P/U FROM CALGARY W/H | AB300: 46214 | AC300: 2028.96 | AD300: 46218 | AE300: 46218
A301: 3086925 | B301: 40 | C301: LIQID | D301: ZORA | E301: 46213 | F301: C | G301: A | H301: 10123006 | I301: 20000912 | J301: 10088045 | K301: S.SPECIAL KEG CHILI RED | L301: 72 | M301: 72 | N301: 72 | O301: 0 | Q301: 80135689 | R301: 0 | S301: 0 | T301: 0 | U301: 504 | V301: 504 | W301: 72 | X301: 0 | Y301: 0 | Z301: 2920 | AA301: NUTRI-GLOBE-P/U FROM CALGARY W/H | AB301: 46219 | AC301: 7992 | AD301: 46218 | AE301: 46218
A302: 3086925 | B302: 50 | C302: LIQID | D302: ZORA | E302: 46213 | F302: C | G302: A | H302: 10123006 | I302: 20000912 | J302: 10052076 | K302: IRS TORTO SWT ORNG OIL SEV | L302: 53 | M302: 53 | N302: 53 | O302: 0 | Q302: 80135689 | R302: 0 | S302: 0 | T302: 0 | U302: 318 | V302: 318 | W302: 53 | X302: 0 | Y302: 0 | Z302: 2920 | AA302: NUTRI-GLOBE-P/U FROM CALGARY W/H | AB302: 46220 | AC302: 1830.09 | AD302: 46218 | AE302: 46218
A303: 3086925 | B303: 60 | C303: LIQID | D303: ZORA | E303: 46213 | F303: C | G303: A | H303: 10123006 | I303: 20000912 | J303: 10007851 | K303: LR RICE SUSHI | L303: 74 | M303: 74 | N303: 74 | O303: 0 | Q303: 80135689 | R303: 0 | S303: 0 | T303: 0 | U303: 592 | V303: 592 | W303: 74 | X303: 0 | Y303: 0 | Z303: 2920 | AA303: NUTRI-GLOBE-P/U FROM CALGARY W/H | AB303: 46220 | AC303: 3735.52 | AD303: 46218 | AE303: 46218
A304: 3086925 | B304: 70 | C304: LIQID | D304: ZORA | E304: 46213 | F304: C | G304: A | H304: 10123006 | I304: 20000912 | J304: 10007843 | K304: LR RICE JASMINE BROWN ORG | L304: 8 | M304: 8 | N304: 8 | O304: 0 | Q304: 80135689 | R304: 0 | S304: 0 | T304: 0 | U304: 64 | V304: 64 | W304: 8 | X304: 0 | Y304: 0 | Z304: 2920 | AA304: NUTRI-GLOBE-P/U FROM CALGARY W/H | AB304: 46232 | AC304: 371.36 | AD304: 46218 | AE304: 46218
A305: 3086925 | B305: 80 | C305: LIQID | D305: ZORA | E305: 46213 | F305: C | G305: A | H305: 10123006 | I305: 20000912 | J305: 10076520 | K305: JW SHORTBREAD FINGERS 115 | L305: 122 | M305: 122 | N305: 122 | O305: 0 | Q305: 80135689 | R305: 0 | S305: 0 | T305: 0 | U305: 1220 | V305: 1220 | W305: 122 | X305: 0 | Y305: 0 | Z305: 2920 | AA305: NUTRI-GLOBE-P/U FROM CALGARY W/H | AB305: 46233 | AC305: 6161 | AD305: 46218 | AE305: 46218
A306: 3086925 | B306: 90 | C306: LIQID | D306: ZORA | E306: 46213 | F306: C | G306: A | H306: 10123006 | I306: 20000912 | J306: 10076782 | K306: JW MINI SHRTBR STARS 1816X | L306: 20 | M306: 20 | N306: 20 | O306: 0 | Q306: 80135689 | R306: 0 | S306: 0 | T306: 0 | U306: 80 | V306: 80 | W306: 20 | X306: 0 | Y306: 0 | Z306: 2920 | AA306: NUTRI-GLOBE-P/U FROM CALGARY W/H | AB306: 46233 | AC306: 438.6 | AD306: 46218 | AE306: 46218
A307: 3087207 | B307: 40 | C307: LIQID | D307: ZORA | E307: 46216 | F307: C | G307: A | H307: 10182593 | I307: 20182593 | J307: 10100028 | K307: BCC CHEESE BURRATA 6x250G | L307: 7 | M307: 0 | N307: 0 | O307: 0 | R307: 0 | S307: 0 | T307: 0 | U307: 89.6 | V307: 0 | W307: 7 | X307: 0 | Y307: 0 | Z307: 2910 | AA307: ZARKY'S FINE FOODS | AC307: 269.71 | AD307: 46218
A308: 3087207 | B308: 110 | C308: LIQID | D308: ZORA | E308: 46216 | F308: C | G308: A | H308: 10182593 | I308: 20182593 | J308: 10061099 | K308: BEL KIRI CHESSE 150G TUB | L308: 4 | M308: 0 | N308: 0 | O308: 0 | R308: 0 | S308: 0 | T308: 0 | U308: 34.04 | V308: 0 | W308: 4 | X308: 0 | Y308: 0 | Z308: 2910 | AA308: ZARKY'S FINE FOODS | AC308: 97.48 | AD308: 46218
A309: 3087225 | B309: 30 | C309: ONIND | D309: ZORA | E309: 46216 | F309: C | G309: A | H309: 10121043 | I309: 20121043 | J309: 10040869 | K309: PMO-PA GNOCCHI SPINACH GF | L309: 30 | M309: 0 | N309: 0 | O309: 0 | R309: 0 | S309: 0 | T309: 0 | U309: 354.9 | V309: 0 | W309: 30 | X309: 0 | Y309: 0 | Z309: 2910 | AA309: SARNIA PRODUCE INC. | AC309: 625.2 | AD309: 46218
A310: 3087375 | B310: 10 | C310: LIQID | D310: ZORA | E310: 46216 | F310: C | G310: A | H310: 10125105 | I310: 20125105 | J310: 10019641 | K310: AGROSGN BRIE CHEVALR TC 650G | L310: 2 | M310: 0 | N310: 0 | O310: 0 | R310: 0 | S310: 0 | T310: 0 | U310: 35.41 | V310: 0 | W310: 2 | X310: 5.2 | Y310: 0 | Z310: 2910 | AA310: ELLIOT LAKE MEATS AND DELI | AC310: 145.81 | AD310: 46219
A311: 3087375 | B311: 30 | C311: LIQID | D311: ZORA | E311: 46216 | F311: C | G311: A | H311: 10125105 | I311: 20125105 | J311: 10100364 | K311: FRANCE BLUE | L311: 2 | M311: 0 | N311: 0 | O311: 0 | R311: 0 | S311: 0 | T311: 0 | U311: 16.16 | V311: 0 | W311: 2 | X311: 0 | Y311: 0 | Z311: 2910 | AA311: ELLIOT LAKE MEATS AND DELI | AC311: 66.54 | AD311: 46219
A312: 3087375 | B312: 40 | C312: LIQID | D312: ZORA | E312: 46216 | F312: C | G312: A | H312: 10125105 | I312: 20125105 | J312: 10019648 | K312: AGROSGN BRIE DBL CREAM 170G | L312: 10 | M312: 0 | N312: 0 | O312: 0 | R312: 0 | S312: 0 | T312: 0 | U312: 100 | V312: 0 | W312: 10 | X312: 0 | Y312: 0 | Z312: 2910 | AA312: ELLIOT LAKE MEATS AND DELI | AC312: 421 | AD312: 46219
A313: 3087375 | B313: 50 | C313: LIQID | D313: ZORA | E313: 46216 | F313: C | G313: A | H313: 10125105 | I313: 20125105 | J313: 10019706 | K313: OKA CHEESE CLASSIQ 1X2.5KG | L313: 1 | M313: 0 | N313: 0 | O313: 0 | R313: 0 | S313: 0 | T313: 0 | U313: 18.58 | V313: 0 | W313: 1 | X313: 2.5 | Y313: 0 | Z313: 2910 | AA313: ELLIOT LAKE MEATS AND DELI | AC313: 74.48 | AD313: 46219
A314: 3087375 | B314: 60 | C314: LIQID | D314: ZORA | E314: 46216 | F314: C | G314: A | H314: 10125105 | I314: 20125105 | J314: 10019706 | K314: OKA CHEESE CLASSIQ 1X2.5KG | L314: 5 | M314: 0 | N314: 0 | O314: 0 | R314: 0 | S314: 0 | T314: 0 | U314: 92.88 | V314: 0 | W314: 5 | X314: 12.5 | Y314: 0 | Z314: 2910 | AA314: ELLIOT LAKE MEATS AND DELI | AC314: 372.38 | AD314: 46219
A315: 3087375 | B315: 70 | C315: LIQID | D315: ZORA | E315: 46216 | F315: C | G315: A | H315: 10125105 | I315: 20125105 | J315: 10019648 | K315: AGROSGN BRIE DBL CREAM 170G | L315: 10 | M315: 0 | N315: 0 | O315: 0 | R315: 0 | S315: 0 | T315: 0 | U315: 100 | V315: 0 | W315: 10 | X315: 0 | Y315: 0 | Z315: 2910 | AA315: ELLIOT LAKE MEATS AND DELI | AC315: 421 | AD315: 46219
A316: 3087375 | B316: 80 | C316: LIQID | D316: ZORA | E316: 46216 | F316: C | G316: A | H316: 10125105 | I316: 20125105 | J316: 10100028 | K316: BCC CHEESE BURRATA 6x250G | L316: 7 | M316: 0 | N316: 0 | O316: 0 | R316: 0 | S316: 0 | T316: 0 | U316: 89.6 | V316: 0 | W316: 7 | X316: 0 | Y316: 0 | Z316: 2910 | AA316: ELLIOT LAKE MEATS AND DELI | AC316: 269.71 | AD316: 46219
A317: 3087375 | B317: 120 | C317: LIQID | D317: ZORA | E317: 46216 | F317: C | G317: A | H317: 10125105 | I317: 20125105 | J317: 10061099 | K317: BEL KIRI CHESSE 150G TUB | L317: 4 | M317: 0 | N317: 0 | O317: 0 | R317: 0 | S317: 0 | T317: 0 | U317: 34.04 | V317: 0 | W317: 4 | X317: 0 | Y317: 0 | Z317: 2910 | AA317: ELLIOT LAKE MEATS AND DELI | AC317: 97.48 | AD317: 46219
A318: 3088637 | B318: 10 | C318: LIQID | D318: ZORA | E318: 46223 | F318: C | G318: A | H318: 10182593 | I318: 20182593 | J318: 10100028 | K318: BCC CHEESE BURRATA 6x250G | L318: 7 | M318: 0 | N318: 0 | O318: 0 | R318: 0 | S318: 0 | T318: 0 | U318: 89.6 | V318: 0 | W318: 7 | X318: 0 | Y318: 0 | Z318: 2910 | AA318: ZARKY'S FINE FOODS | AC318: 269.71 | AD318: 46225
... A334: 3088764 | B334: 50 | C334: ONIND | D334: ZORA | E334: 46223 | F334: C | G334: A | H334: 10300082 | I334: 20300082 | J334: 10054147 | K334: CB CORNED BEEF | L334: 50 | M334: 0 | N334: 0 | O334: 0 | R334: 0 | S334: 0 | T334: 0 | U334: 232.5 | V334: 0 | W334: 50 | X334: 0 | Y334: 0 | Z334: 2910 | AA334: POSTICINO RISTORANTE | AC334: 523.5 | AD334: 46225
A335: 3088984 | B335: 10 | C335: LIQID | D335: ZORA | E335: 46224 | F335: C | G335: A | H335: 10062506 | I335: 20062506 | J335: 10007849 | K335: LR RICE BROWN SHRT GRAIN ORG | L335: 1 | M335: 1 | N335: 1 | O335: 0 | Q335: 80138304 | R335: 0 | S335: 0 | T335: 0 | U335: 9 | V335: 9 | W335: 1 | X335: 0 | Y335: 0 | Z335: 2920 | AA335: LO-BOY MARKET CLEARANCE | AB335: 46224 | AC335: 36.92 | AD335: 46227 | AE335: 46227
A336: 3088984 | B336: 20 | C336: LIQID | D336: ZORA | E336: 46224 | F336: C | G336: A | H336: 10062506 | I336: 20062506 | J336: 10076532 | K336: JW SHORTBRD CHOCO CHIP 1149 | L336: 3 | M336: 3 | N336: 3 | O336: 0 | Q336: 80138304 | R336: 0 | S336: 0 | T336: 0 | U336: 18 | V336: 18 | W336: 3 | X336: 0 | Y336: 0 | Z336: 2920 | AA336: LO-BOY MARKET CLEARANCE | AB336: 46233 | AC336: 79.92 | AD336: 46227 | AE336: 46227
A337: 3088984 | B337: 30 | C337: LIQID | D337: ZORA | E337: 46224 | F337: C | G337: A | H337: 10062506 | I337: 20062506 | J337: 10050324 | K337: SHARWOODS CHUTNEY MANGO FS | L337: 10 | M337: 10 | N337: 10 | O337: 0 | Q337: 80138304 | R337: 0 | S337: 0 | T337: 0 | U337: 100 | V337: 100 | W337: 10 | X337: 0 | Y337: 0 | Z337: 2920 | AA337: LO-BOY MARKET CLEARANCE | AB337: 46234 | AC337: 379.7 | AD337: 46227 | AE337: 46227
A338: 3088984 | B338: 40 | C338: LIQID | D338: ZORA | E338: 46224 | F338: C | G338: A | H338: 10062506 | I338: 20062506 | J338: 10083460 | K338: MCV DIGESTIVE MK CHOC 18591 | L338: 15 | M338: 0 | N338: 0 | O338: 0 | R338: 0 | S338: 0 | T338: 0 | U338: 150 | V338: 0 | W338: 15 | X338: 0 | Y338: 0 | Z338: 2920 | AA338: LO-BOY MARKET CLEARANCE | AC338: 427.2 | AD338: 46227
A339: 3088984 | B339: 50 | C339: LIQID | D339: ZORA | E339: 46224 | F339: C | G339: A | H339: 10062506 | I339: 20062506 | J339: 10031164 | K339: CLIPPER RISE & SHINE ORG | L339: 6 | M339: 6 | N339: 6 | O339: 0 | Q339: 80138304 | R339: 0 | S339: 0 | T339: 0 | U339: 30 | V339: 30 | W339: 6 | X339: 0 | Y339: 0 | Z339: 2920 | AA339: LO-BOY MARKET CLEARANCE | AB339: 46247 | AC339: 114.9 | AD339: 46227 | AE339: 46227
A340: 3088984 | B340: 60 | C340: LIQID | D340: ZORA | E340: 46224 | F340: C | G340: A | H340: 10062506 | I340: 20062506 | J340: 10017617 | K340: TST SAUCE MANGO CURRY | L340: 38 | M340: 38 | N340: 38 | O340: 0 | Q340: 80138304 | R340: 0 | S340: 0 | T340: 0 | U340: 190 | V340: 190 | W340: 38 | X340: 0 | Y340: 0 | Z340: 2920 | AA340: LO-BOY MARKET CLEARANCE | AB340: 46265 | AC340: 587.86 | AD340: 46227 | AE340: 46227
A341: 3089006 | B341: 20 | C341: LIQID | D341: ZORA | E341: 46224 | F341: C | G341: A | H341: 10123006 | I341: 20000912 | J341: 10083460 | K341: MCV DIGESTIVE MK CHOC 18591 | L341: 15 | M341: 0 | N341: 0 | O341: 0 | R341: 0 | S341: 0 | T341: 0 | U341: 75 | V341: 0 | W341: 15 | X341: 0 | Y341: 0 | Z341: 2920 | AA341: NUTRI-GLOBE-P/U FROM CALGARY W/H | AC341: 427.2 | AD341: 46227
A342: 3089006 | B342: 30 | C342: LIQID | D342: ZORA | E342: 46224 | F342: C | G342: A | H342: 10123006 | I342: 20000912 | J342: 10050485 | K342: NUPST VEGAN BOLOGNESE | L342: 48 | M342: 48 | N342: 48 | O342: 0 | Q342: 80138660 | R342: 0 | S342: 0 | T342: 0 | U342: 144 | V342: 144 | W342: 48 | X342: 0 | Y342: 0 | Z342: 2920 | AA342: NUTRI-GLOBE-P/U FROM CALGARY W/H | AB342: 46237 | AC342: 778.56 | AD342: 46227 | AE342: 46227
A343: 3089006 | B343: 40 | C343: LIQID | D343: ZORA | E343: 46224 | F343: C | G343: A | H343: 10123006 | I343: 20000912 | J343: 10050486 | K343: NUPST VEGAN CHILI | L343: 21 | M343: 21 | N343: 21 | O343: 0 | Q343: 80138660 | R343: 0 | S343: 0 | T343: 0 | U343: 63 | V343: 63 | W343: 21 | X343: 0 | Y343: 0 | Z343: 2920 | AA343: NUTRI-GLOBE-P/U FROM CALGARY W/H | AB343: 46237 | AC343: 346.92 | AD343: 46227 | AE343: 46227
A344: 3089006 | B344: 50 | C344: LIQID | D344: ZORA | E344: 46224 | F344: C | G344: A | H344: 10123006 | I344: 20000912 | J344: 10057233 | K344: KKM OYSTER FLAVORED SAUCE | L344: 92 | M344: 92 | N344: 92 | O344: 0 | Q344: 80138660 | R344: 0 | S344: 0 | T344: 0 | U344: 736 | V344: 736 | W344: 92 | X344: 0 | Y344: 0 | Z344: 2920 | AA344: NUTRI-GLOBE-P/U FROM CALGARY W/H | AB344: 46241 | AC344: 2840.04 | AD344: 46227 | AE344: 46227
A345: 3089006 | B345: 60 | C345: LIQID | D345: ZORA | E345: 46224 | F345: C | G345: A | H345: 10123006 | I345: 20000912 | J345: 10049305 | K345: CERES JUICE GUAVA | L345: 81 | M345: 81 | N345: 81 | O345: 0 | Q345: 80138660 | R345: 0 | S345: 0 | T345: 0 | U345: 405 | V345: 405 | W345: 81 | X345: 0 | Y345: 0 | Z345: 2920 | AA345: NUTRI-GLOBE-P/U FROM CALGARY W/H | AB345: 46247 | AC345: 2455.11 | AD345: 46227 | AE345: 46227
A346: 3089402 | B346: 50 | C346: LIQID | D346: ZORA | E346: 46225 | F346: C | G346: A | H346: 10150032 | I346: 20901194 | J346: 10076880 | K346: KKF FZN BREAD WHITE | L346: 70 | M346: 70 | N346: 70 | O346: 0 | Q346: 80138419 | R346: 0 | S346: 0 | T346: 0 | U346: 612.5 | V346: 612.5 | W346: 70 | X346: 0 | Y346: 0 | Z346: 2910 | AA346: COUNTRY TRADITIONS FROZEN FOODS FZ | AC346: 1554.7 | AD346: 46227 | AE346: 46227
A347: 3089716 | B347: 10 | C347: LIQID | D347: ZORA | E347: 46226 | F347: C | G347: A | H347: 10150032 | I347: 20150032 | J347: 10100028 | K347: BCC CHEESE BURRATA 6x250G | L347: 7 | M347: 0 | N347: 0 | O347: 0 | R347: 0 | S347: 0 | T347: 0 | U347: 89.6 | V347: 0 | W347: 7 | X347: 0 | Y347: 0 | Z347: 2910 | AA347: COUNTRY TRADITIONS FROZEN FOODS | AC347: 269.71 | AD347: 46230
A348: 3089716 | B348: 110 | C348: LIQID | D348: ZORA | E348: 46226 | F348: C | G348: A | H348: 10150032 | I348: 20150032 | J348: 10061013 | K348: BEL BOUR 150GR SHAL & CHIVES | L348: 24 | M348: 0 | N348: 0 | O348: 0 | R348: 0 | S348: 0 | T348: 0 | U348: 213.36 | V348: 0 | W348: 24 | X348: 0 | Y348: 0 | Z348: 2910 | AA348: COUNTRY TRADITIONS FROZEN FOODS | AC348: 619.2 | AD348: 46230
A349: 3090119 | B349: 10 | C349: ATIND | D349: ZORA | E349: 46230 | F349: C | G349: A | H349: 10621400 | I349: 20621400 | J349: 10061060 | K349: BEL TLC CHEESE DIPPERS 1X | L349: 10 | M349: 0 | N349: 0 | O349: 0 | R349: 0 | S349: 0 | T349: 0 | U349: 53.5 | V349: 0 | W349: 10 | X349: 0 | Y349: 0 | Z349: 2910 | AA349: WARD FOODS LTD | AC349: 154.9 | AD349: 46234
A350: 3090119 | B350: 30 | C350: ATIND | D350: ZORA | E350: 46230 | F350: C | G350: A | H350: 10621400 | I350: 20621400 | J350: 10061099 | K350: BEL KIRI CHESSE 150G TUB | L350: 3 | M350: 0 | N350: 0 | O350: 0 | R350: 0 | S350: 0 | T350: 0 | U350: 25.53 | V350: 0 | W350: 3 | X350: 0 | Y350: 0 | Z350: 2910 | AA350: WARD FOODS LTD | AC350: 74.55 | AD350: 46234
A351: 3090119 | B351: 60 | C351: ATIND | D351: ZORA | E351: 46230 | F351: C | G351: A | H351: 10621400 | I351: 20621400 | J351: 10033021 | K351: SABANA QUESO FRESCO | L351: 15 | M351: 0 | N351: 0 | O351: 0 | R351: 0 | S351: 0 | T351: 0 | U351: 200.85 | V351: 0 | W351: 15 | X351: 0 | Y351: 0 | Z351: 2910 | AA351: WARD FOODS LTD | AC351: 568.8 | AD351: 46234
...

Sheet Price List
A1: BDM | B1: Brand Name | C1: Material | D1: Description | E1: Pack | F1: Size | G1: Pricing Date | H1: 1 - Store Door | I1: 2 - Wholesale | J1: Plant | K1: Sold by Wt
A2: NANCY QUISPE PT | B2: JARRITOS | C2: 10001116 | D2: JARRITOS TAMARIND SOFT DRINK | E2: 24 | F2: 370 ML | G2: 46238 | H2: 38.87 | I2: 34.66 | J2: 2910 | K2: 0
A3: NANCY QUISPE PT | B3: JARRITOS | C3: 10001117 | D3: JARRITOS MANDARIN SOFT DRINK | E3: 24 | F3: 370 ML | G3: 46238 | H3: 38.87 | I3: 34.66 | J3: 2910 | K3: 0
A4: NANCY QUISPE PT | B4: JARRITOS | C4: 10001118 | D4: JARRITOS COLA SOFT DRINK | E4: 24 | F4: 370 ML | G4: 46238 | H4: 38.87 | I4: 34.66 | J4: 2910 | K4: 0
A5: NANCY QUISPE PT | B5: JARRITOS | C5: 10001119 | D5: JARRITOS GUAVA SOFT DRINK | E5: 24 | F5: 370 ML | G5: 46238 | H5: 38.87 | I5: 34.66 | J5: 2910 | K5: 0
A6: NANCY QUISPE PT | B6: JARRITOS | C6: 10001120 | D6: JARRITOS LIME SOFT DRINK | E6: 24 | F6: 370 ML | G6: 46238 | H6: 38.87 | I6: 34.66 | J6: 2910 | K6: 0
A7: NANCY QUISPE PT | B7: JARRITOS | C7: 10001121 | D7: JARRITOS PINEAPPLE SOFT DRINK | E7: 24 | F7: 370 ML | G7: 46238 | H7: 38.87 | I7: 34.66 | J7: 2910 | K7: 0
A8: NANCY QUISPE PT | B8: JARRITOS | C8: 10001122 | D8: JARRITOS FRUIT PUNCH SOFT DRINK | E8: 24 | F8: 370 ML | G8: 46238 | H8: 38.87 | I8: 34.66 | J8: 2910 | K8: 0
A9: NANCY QUISPE PT | B9: JARRITOS | C9: 10001123 | D9: JARRITOS GRAPEFRUIT SOFT DRINK | E9: 24 | F9: 370 ML | G9: 46238 | H9: 38.87 | I9: 34.66 | J9: 2910 | K9: 0
A10: NANCY QUISPE PT | B10: JARRITOS | C10: 10001126 | D10: JARRITOS STRAWBERRY SOFT DRINK | E10: 24 | F10: 370 ML | G10: 46238 | H10: 38.87 | I10: 34.66 | J10: 2910 | K10: 0
A11: NANCY QUISPE PT | B11: JARRITOS | C11: 10001127 | D11: JARRITOS MANGO SOFT DRINK | E11: 24 | F11: 370 ML | G11: 46238 | H11: 38.87 | I11: 34.66 | J11: 2910 | K11: 0
A12: NANCY QUISPE PT | B12: SANGRIA SENORIAL | C12: 10001128 | D12: SANGRIA SENORIAL GRAPE CIDER SOFT DRINK | E12: 24 | F12: 330 ML | G12: 46238 | H12: 37.68 | I12: 33.6 | J12: 2910 | K12: 0
A13: NANCY QUISPE PT | B13: JARRITOS | C13: 10001134 | D13: JARRITOS WATERMELON SOFT DRINK | E13: 24 | F13: 370 ML | G13: 46238 | H13: 38.87 | I13: 34.66 | J13: 2910 | K13: 0
... A3297: TRACEY LAWRENCE | B3297: SNACK FACTORY | C3297: 50100024 | D3297: Snack Factory Rack Walmart | E3297: 1 | F3297: RACK | G3297: 46238 | H3297: 0 | I3297: 0 | J3297: 2910 | K3297: 0

Sheet Old report
A1: BDM | B1: Material Group Name | C1: Material | D1: Material Description | E1: Sold by KG | F1: Pack | G1: Size | H1: Plant | I1: Plant Name | J1: Batch | K1: Storage Location | L1: Shelf Life Expiration Date | M1: Unrestricted Stock | N1: Unique Key | O1: Allocation | P1: Available
A2: =_xlfn.XLOOKUP(C:C,'Price List'!C:C,'Price List'!A:A) -> JAMES TYSON | B2: VEGGIES MADE GREAT | C2: 10015389 | D2: VMG BRC&CHS BRKFST BKE POTAT | E2: =_xlfn.XLOOKUP(C:C,'Price List'!C:C,'Price List'!K:K) -> 0 | F2: =_xlfn.XLOOKUP(C:C,'Price List'!C:C,'Price List'!E:E) -> 8 | G2: =_xlfn.XLOOKUP(C:C,'Price List'!C:C,'Price List'!F:F) -> 340 GR | H2: 2925 | I2: Lineage Calgary CS | J2: 260516 | K2: 1100 | L2: 46158 | M2: 29 | N2: =C2 & "_" & 2910 -> 10015389_2910 | O2: =_xlfn.XLOOKUP(N2,Allocation!H:H,Allocation!C:C,0) -> 0 | P2: =M2-O2 -> 29
A3: =_xlfn.XLOOKUP(C:C,'Price List'!C:C,'Price List'!A:A) -> NISA DELEON | B3: CLIF BAR | C3: 10050613 | D3: CB WH CHOC MACAD NUT | E3: =_xlfn.XLOOKUP(C:C,'Price List'!C:C,'Price List'!K:K) -> 0 | F3: =_xlfn.XLOOKUP(C:C,'Price List'!C:C,'Price List'!E:E) -> 12 | G3: =_xlfn.XLOOKUP(C:C,'Price List'!C:C,'Price List'!F:F) -> 68 GR | H3: 2920 | I3: TOL Calgary | J3: IN15925012 | K3: 1100 | L3: 46161 | M3: 49 | N3: =C3 & "_" & 2910 -> 10050613_2910 | O3: =_xlfn.XLOOKUP(N3,Allocation!H:H,Allocation!C:C,0) -> 0 | P3: =M3-O3 -> 49
A4: =_xlfn.XLOOKUP(C:C,'Price List'!C:C,'Price List'!A:A) -> AMOL PRAKASH | B4: KINNIKINNICK | C4: 10015807 | D4: KKF FZN DONUT CHOC DIPPED | E4: =_xlfn.XLOOKUP(C:C,'Price List'!C:C,'Price List'!K:K) -> 0 | F4: =_xlfn.XLOOKUP(C:C,'Price List'!C:C,'Price List'!E:E) -> 8 | G4: =_xlfn.XLOOKUP(C:C,'Price List'!C:C,'Price List'!F:F) -> 320 GR | H4: 2925 | I4: Lineage Calgary CS | J4: 2026MA25 | K4: 1100 | L4: 46167 | M4: 6 | N4: =C4 & "_" & 2910 -> 10015807_2910 | O4: =_xlfn.XLOOKUP(N4,Allocation!H:H,Allocation!C:C,0) -> 0 | P4: =M4-O4 -> 6
A5: =_xlfn.XLOOKUP(C:C,'Price List'!C:C,'Price List'!A:A) -> WARREN PARK | B5: LAID BACK SNACKS | C5: 10020850 | D5: LBS HEARTY TAMARI 45G PP | E5: =_xlfn.XLOOKUP(C:C,'Price List'!C:C,'Price List'!K:K) -> 0 | F5: =_xlfn.XLOOKUP(C:C,'Price List'!C:C,'Price List'!E:E) -> 20 | G5: =_xlfn.XLOOKUP(C:C,'Price List'!C:C,'Price List'!F:F) -> 45 GR | H5: 2920 | I5: TOL Calgary | J5: 20250828 | K5: 1100 | L5: 46170 | M5: 5 | N5: =C5 & "_" & 2910 -> 10020850_2910 | O5: =_xlfn.XLOOKUP(N5,Allocation!H:H,Allocation!C:C,0) -> 0 | P5: =M5-O5 -> 5
A6: =_xlfn.XLOOKUP(C:C,'Price List'!C:C,'Price List'!A:A) -> JASON MULDOON PT | B6: CARL BUDDIG | C6: 10054147 | D6: CB CORNED BEEF | E6: =_xlfn.XLOOKUP(C:C,'Price List'!C:C,'Price List'!K:K) -> 0 | F6: =_xlfn.XLOOKUP(C:C,'Price List'!C:C,'Price List'!E:E) -> 12 | G6: =_xlfn.XLOOKUP(C:C,'Price List'!C:C,'Price List'!F:F) -> 55 GR | H6: 2920 | I6: TOL Calgary | J6: 26056 | K6: 1100 | L6: 46172 | M6: 7 | N6: =C6 & "_" & 2910 -> 10054147_2910 | O6: =_xlfn.XLOOKUP(N6,Allocation!H:H,Allocation!C:C,0) -> 0 | P6: =M6-O6 -> 7
A7: =_xlfn.XLOOKUP(C:C,'Price List'!C:C,'Price List'!A:A) -> SAMANTHA RODRIGUES GB | B7: MCVITIES | C7: 30083538 | D7: MCV DISP - DIGESTIVE ORIG | E7: =_xlfn.XLOOKUP(C:C,'Price List'!C:C,'Price List'!K:K) -> 0 | F7: =_xlfn.XLOOKUP(C:C,'Price List'!C:C,'Price List'!E:E) -> 48 | G7: =_xlfn.XLOOKUP(C:C,'Price List'!C:C,'Price List'!F:F) -> SHIPPER | H7: 2920 | I7: TOL Calgary | J7: 1000000033 | K7: 1100 | L7: 46172 | M7: 3 | N7: =C7 & "_" & 2910 -> 30083538_2910 | O7: =_xlfn.XLOOKUP(N7,Allocation!H:H,Allocation!C:C,0) -> 0 | P7: =M7-O7 -> 3
A8: =_xlfn.XLOOKUP(C:C,'Price List'!C:C,'Price List'!A:A) -> NANCY QUISPE PT | B8: THE SPICE TAILOR | C8: 10017604 | D8: TST PUNJAB CHICKPEA MASALA | E8: =_xlfn.XLOOKUP(C:C,'Price List'!C:C,'Price List'!K:K) -> 0 | F8: =_xlfn.XLOOKUP(C:C,'Price List'!C:C,'Price List'!E:E) -> 5 | G8: =_xlfn.XLOOKUP(C:C,'Price List'!C:C,'Price List'!F:F) -> 375 ML | H8: 2920 | I8: TOL Calgary | J8: 4183T | K8: 1100 | L8: 46173 | M8: 145 | N8: =C8 & "_" & 2910 -> 10017604_2910 | O8: =_xlfn.XLOOKUP(N8,Allocation!H:H,Allocation!C:C,0) -> 0 | P8: =M8-O8 -> 145
A9: =_xlfn.XLOOKUP(C:C,'Price List'!C:C,'Price List'!A:A) -> MICHELLE JEWELL NT | B9: SCHAR | C9: 10038127 | D9: SCHAR BREAD DELI SOURDOH GF | E9: =_xlfn.XLOOKUP(C:C,'Price List'!C:C,'Price List'!K:K) -> 0 | F9: =_xlfn.XLOOKUP(C:C,'Price List'!C:C,'Price List'!E:E) -> 5 | G9: =_xlfn.XLOOKUP(C:C,'Price List'!C:C,'Price List'!F:F) -> 240 GR | H9: 2920 | I9: TOL Calgary | J9: 260601D | K9: 1100 | L9: 46174 | M9: 119 | N9: =C9 & "_" & 2910 -> 10038127_2910 | O9: =_xlfn.XLOOKUP(N9,Allocation!H:H,Allocation!C:C,0) -> 0 | P9: =M9-O9 -> 119
A10: =_xlfn.XLOOKUP(C:C,'Price List'!C:C,'Price List'!A:A) -> NIKISHA MOHAMMED | B10: GREEN & BLACKS | C10: 10043078 | D10: G&B DARK CHOC GINGER ORG | E10: =_xlfn.XLOOKUP(C:C,'Price List'!C:C,'Price List'!K:K) -> 0 | F10: =_xlfn.XLOOKUP(C:C,'Price List'!C:C,'Price List'!E:E) -> 10 | G10: =_xlfn.XLOOKUP(C:C,'Price List'!C:C,'Price List'!F:F) -> 90 GR | H10: 2920 | I10: TOL Calgary | J10: OWR0344931 | K10: 1100 | L10: 46179 | M10: 2 | N10: =C10 & "_" & 2910 -> 10043078_2910 | O10: =_xlfn.XLOOKUP(N10,Allocation!H:H,Allocation!C:C,0) -> 0 | P10: =M10-O10 -> 2
A11: =_xlfn.XLOOKUP(C:C,'Price List'!C:C,'Price List'!A:A) -> NIKISHA MOHAMMED | B11: MY COOKING BOX | C11: 10041273 | D11: MCB PIZZA ITALIAN PIZZA CRST | E11: =_xlfn.XLOOKUP(C:C,'Price List'!C:C,'Price List'!K:K) -> 0 | F11: =_xlfn.XLOOKUP(C:C,'Price List'!C:C,'Price List'!E:E) -> 7 | G11: =_xlfn.XLOOKUP(C:C,'Price List'!C:C,'Price List'!F:F) -> 933 GR | H11: 2920 | I11: TOL Calgary | J11: LT250325CP | K11: 1100 | L11: 46179 | M11: 25 | N11: =C11 & "_" & 2910 -> 10041273_2910 | O11: =_xlfn.XLOOKUP(N11,Allocation!H:H,Allocation!C:C,0) -> 0 | P11: =M11-O11 -> 25
A12: =_xlfn.XLOOKUP(C:C,'Price List'!C:C,'Price List'!A:A) -> NIKISHA MOHAMMED | B12: MY COOKING BOX | C12: 10041273 | D12: MCB PIZZA ITALIAN PIZZA CRST | E12: =_xlfn.XLOOKUP(C:C,'Price List'!C:C,'Price List'!K:K) -> 0 | F12: =_xlfn.XLOOKUP(C:C,'Price List'!C:C,'Price List'!E:E) -> 7 | G12: =_xlfn.XLOOKUP(C:C,'Price List'!C:C,'Price List'!F:F) -> 933 GR | H12: 2920 | I12: TOL Calgary | J12: LT260325CP | K12: 1100 | L12: 46179 | M12: 45 | N12: =C12 & "_" & 2910 -> 10041273_2910 | O12: =_xlfn.XLOOKUP(N12,Allocation!H:H,Allocation!C:C,0) -> 0 | P12: =M12-O12 -> 45
A13: =_xlfn.XLOOKUP(C:C,'Price List'!C:C,'Price List'!A:A) -> ANABELA NEVES PR | B13: BEL BOURSIN | C13: 10061010 | D13: BEL BOUR 150G GARLIC & HERB | E13: =_xlfn.XLOOKUP(C:C,'Price List'!C:C,'Price List'!K:K) -> 0 | F13: =_xlfn.XLOOKUP(C:C,'Price List'!C:C,'Price List'!E:E) -> 12 | G13: =_xlfn.XLOOKUP(C:C,'Price List'!C:C,'Price List'!F:F) -> 150 GR | H13: 2920 | I13: TOL Calgary | J13: AG0431J | K13: 1100 | L13: 46180 | M13: 42 | N13: =C13 & "_" & 2910 -> 10061010_2910 | O13: =_xlfn.XLOOKUP(N13,Allocation!H:H,Allocation!C:C,0) -> 0 | P13: =M13-O13 -> 42
... A24: =_xlfn.XLOOKUP(C:C,'Price List'!C:C,'Price List'!A:A) -> AMOL PRAKASH | B24: KINNIKINNICK | C24: 10015808 | D24: KKF FZN DONUTS MAPLE GLAZED | E24: =_xlfn.XLOOKUP(C:C,'Price List'!C:C,'Price List'!K:K) -> 0 | F24: =_xlfn.XLOOKUP(C:C,'Price List'!C:C,'Price List'!E:E) -> 8 | G24: =_xlfn.XLOOKUP(C:C,'Price List'!C:C,'Price List'!F:F) -> 320 GR | H24: 2925 | I24: Lineage Calgary CS | J24: 2026JN15 | K24: 1100 | L24: 46188 | M24: 8 | N24: =C24 & "_" & 2910 -> 10015808_2910 | O24: =_xlfn.XLOOKUP(N24,Allocation!H:H,Allocation!C:C,0) -> 0 | P24: =M24-O24 -> 8
A25: =_xlfn.XLOOKUP(C:C,'Price List'!C:C,'Price List'!A:A) -> SERENA LEE PR | B25: AGROPUR | C25: 10019641 | D25: AGROSGN BRIE CHEVALR TC 650G | E25: KG | F25: =_xlfn.XLOOKUP(C:C,'Price List'!C:C,'Price List'!E:E) -> 4 | G25: =_xlfn.XLOOKUP(C:C,'Price List'!C:C,'Price List'!F:F) -> 650 GR | H25: 2920 | I25: TOL Calgary | J25: 20260616 | K25: 1100 | L25: 46189 | M25: 2 | N25: =C25 & "_" & 2910 -> 10019641_2910 | O25: =_xlfn.XLOOKUP(N25,Allocation!H:H,Allocation!C:C,0) -> 0 | P25: =M25-O25 -> 2
A26: =_xlfn.XLOOKUP(C:C,'Price List'!C:C,'Price List'!A:A) -> SERENA LEE PR | B26: AGROPUR | C26: 10019704 | D26: OKA CHEESE ORIGINAL 1X2.5KG | E26: KG | F26: =_xlfn.XLOOKUP(C:C,'Price List'!C:C,'Price List'!E:E) -> 1 | G26: =_xlfn.XLOOKUP(C:C,'Price List'!C:C,'Price List'!F:F) -> 2.5 KG | H26: 2920 | I26: TOL Calgary | J26: 20260616 | K26: 1100 | L26: 46189 | M26: 1 | N26: =C26 & "_" & 2910 -> 10019704_2910 | O26: =_xlfn.XLOOKUP(N26,Allocation!H:H,Allocation!C:C,0) -> 0 | P26: =M26-O26 -> 1
A27: =_xlfn.XLOOKUP(C:C,'Price List'!C:C,'Price List'!A:A) -> SERENA LEE PR | B27: AGROPUR | C27: 10019704 | D27: OKA CHEESE ORIGINAL 1X2.5KG | E27: KG | F27: =_xlfn.XLOOKUP(C:C,'Price List'!C:C,'Price List'!E:E) -> 1 | G27: =_xlfn.XLOOKUP(C:C,'Price List'!C:C,'Price List'!F:F) -> 2.5 KG | H27: 2920 | I27: TOL Calgary | J27: 20260617 | K27: 1100 | L27: 46190 | M27: 2 | N27: =C27 & "_" & 2910 -> 10019704_2910 | O27: =_xlfn.XLOOKUP(N27,Allocation!H:H,Allocation!C:C,0) -> 0 | P27: =M27-O27 -> 2
A28: =_xlfn.XLOOKUP(C:C,'Price List'!C:C,'Price List'!A:A) -> ANABELA NEVES PR | B28: STONETOWN ARTISAN CH | C28: 10052112 | D28: STW 170G FARMSTD EMMENTAL | E28: =_xlfn.XLOOKUP(C:C,'Price List'!C:C,'Price List'!K:K) -> 0 | F28: =_xlfn.XLOOKUP(C:C,'Price List'!C:C,'Price List'!E:E) -> 12 | G28: =_xlfn.XLOOKUP(C:C,'Price List'!C:C,'Price List'!F:F) -> 170 GR | H28: 2920 | I28: TOL Calgary | J28: 9.9.25/30. | K28: 1100 | L28: 46191 | M28: 3 | N28: =C28 & "_" & 2910 -> 10052112_2910 | O28: =_xlfn.XLOOKUP(N28,Allocation!H:H,Allocation!C:C,0) -> 0 | P28: =M28-O28 -> 3
A29: =_xlfn.XLOOKUP(C:C,'Price List'!C:C,'Price List'!A:A) -> TRACEY LAWRENCE | B29: KETTLE CHIPS | C29: 10066215 | D29: KC HONEY DIJON 56G GF | E29: =_xlfn.XLOOKUP(C:C,'Price List'!C:C,'Price List'!K:K) -> 0 | F29: =_xlfn.XLOOKUP(C:C,'Price List'!C:C,'Price List'!E:E) -> 24 | G29: =_xlfn.XLOOKUP(C:C,'Price List'!C:C,'Price List'!F:F) -> 56 GR | H29: 2920 | I29: TOL Calgary | J29: 20JUN2026 | K29: 1100 | L29: 46193 | M29: 7 | N29: =C29 & "_" & 2910 -> 10066215_2910 | O29: =_xlfn.XLOOKUP(N29,Allocation!H:H,Allocation!C:C,0) -> 0 | P29: =M29-O29 -> 7
A30: =_xlfn.XLOOKUP(C:C,'Price List'!C:C,'Price List'!A:A) -> NATASHA KING PR | B30: KROON | C30: 10030187 | D30: KROON GOUDA MEDIUM | E30: KG | F30: =_xlfn.XLOOKUP(C:C,'Price List'!C:C,'Price List'!E:E) -> 1 | G30: =_xlfn.XLOOKUP(C:C,'Price List'!C:C,'Price List'!F:F) -> 4.5 KG | H30: 2920 | I30: TOL Calgary | J30: 10G8BR1 | K30: 1100 | L30: 46193 | M30: 1 | N30: =C30 & "_" & 2910 -> 10030187_2910 | O30: =_xlfn.XLOOKUP(N30,Allocation!H:H,Allocation!C:C,0) -> 0 | P30: =M30-O30 -> 1
A31: =_xlfn.XLOOKUP(C:C,'Price List'!C:C,'Price List'!A:A) -> SERENA LEE PR | B31: AGROPUR | C31: 10019780 | D31: SNO BLACK BOMBER 1X2KG | E31: KG | F31: =_xlfn.XLOOKUP(C:C,'Price List'!C:C,'Price List'!E:E) -> 1 | G31: =_xlfn.XLOOKUP(C:C,'Price List'!C:C,'Price List'!F:F) -> 2 KG | H31: 2920 | I31: TOL Calgary | J31: 20260622 | K31: 1100 | L31: 46195 | M31: 28 | N31: =C31 & "_" & 2910 -> 10019780_2910 | O31: =_xlfn.XLOOKUP(N31,Allocation!H:H,Allocation!C:C,0) -> 0 | P31: =M31-O31 -> 28
A32: =_xlfn.XLOOKUP(C:C,'Price List'!C:C,'Price List'!A:A) -> ASIF AHMAD GB | B32: BLUE DIAMOND BEVERAG | C32: 10016405 | D32: BD ALM BREEZE UNSWT CHOCOLAT | E32: =_xlfn.XLOOKUP(C:C,'Price List'!C:C,'Price List'!K:K) -> 0 | F32: =_xlfn.XLOOKUP(C:C,'Price List'!C:C,'Price List'!E:E) -> 12 | G32: =_xlfn.XLOOKUP(C:C,'Price List'!C:C,'Price List'!F:F) -> 946 ML | H32: 2920 | I32: TOL Calgary | J32: 6AT25173A | K32: 1100 | L32: 46195 | M32: 72 | N32: =C32 & "_" & 2910 -> 10016405_2910 | O32: =_xlfn.XLOOKUP(N32,Allocation!H:H,Allocation!C:C,0) -> 0 | P32: =M32-O32 -> 72
A33: =_xlfn.XLOOKUP(C:C,'Price List'!C:C,'Price List'!A:A) -> ANABELA NEVES PR | B33: BOTHWELL CHEESE | C33: 10100089 | D33: BC RED HOT CHILI MJ | E33: =_xlfn.XLOOKUP(C:C,'Price List'!C:C,'Price List'!K:K) -> 0 | F33: =_xlfn.XLOOKUP(C:C,'Price List'!C:C,'Price List'!E:E) -> 12 | G33: =_xlfn.XLOOKUP(C:C,'Price List'!C:C,'Price List'!F:F) -> 540 GR | H33: 2920 | I33: TOL Calgary | J33: 20251027 | K33: 1100 | L33: 46197 | M33: 10 | N33: =C33 & "_" & 2910 -> 10100089_2910 | O33: =_xlfn.XLOOKUP(N33,Allocation!H:H,Allocation!C:C,0) -> 0 | P33: =M33-O33 -> 10
A34: =_xlfn.XLOOKUP(C:C,'Price List'!C:C,'Price List'!A:A) -> WARREN PARK | B34: LAID BACK SNACKS | C34: 10020851 | D34: LBS POSH PRALINE ALMD 45G | E34: =_xlfn.XLOOKUP(C:C,'Price List'!C:C,'Price List'!K:K) -> 0 | F34: =_xlfn.XLOOKUP(C:C,'Price List'!C:C,'Price List'!E:E) -> 20 | G34: =_xlfn.XLOOKUP(C:C,'Price List'!C:C,'Price List'!F:F) -> 45 GR | H34: 2920 | I34: TOL Calgary | J34: 20250924 | K34: 1100 | L34: 46197 | M34: 4 | N34: =C34 & "_" & 2910 -> 10020851_2910 | O34: =_xlfn.XLOOKUP(N34,Allocation!H:H,Allocation!C:C,0) -> 0 | P34: =M34-O34 -> 4
A35: =_xlfn.XLOOKUP(C:C,'Price List'!C:C,'Price List'!A:A) -> ANABELA NEVES PR | B35: ALIMENTIAS SPAIN CHE | C35: 10013759 | D35: BULK SHP CHS AGD IN CASKS | E35: KG | F35: =_xlfn.XLOOKUP(C:C,'Price List'!C:C,'Price List'!E:E) -> 2 | G35: =_xlfn.XLOOKUP(C:C,'Price List'!C:C,'Price List'!F:F) -> 3 KG | H35: 2920 | I35: TOL Calgary | J35: 17625 | K35: 1100 | L35: 46198 | M35: 2 | N35: =C35 & "_" & 2910 -> 10013759_2910 | O35: =_xlfn.XLOOKUP(N35,Allocation!H:H,Allocation!C:C,0) -> 0 | P35: =M35-O35 -> 2
A36: =_xlfn.XLOOKUP(C:C,'Price List'!C:C,'Price List'!A:A) -> NATASHA KING PR | B36: TRADITIONAL CHEESE | C36: 10097047 | D36: TRD IRISH CHED BK PEP CHIVE | E36: =_xlfn.XLOOKUP(C:C,'Price List'!C:C,'Price List'!K:K) -> 0 | F36: =_xlfn.XLOOKUP(C:C,'Price List'!C:C,'Price List'!E:E) -> 8 | G36: =_xlfn.XLOOKUP(C:C,'Price List'!C:C,'Price List'!F:F) -> 150 GR | H36: 2920 | I36: TOL Calgary | J36: LOT-110761 | K36: 1100 | L36: 46198 | M36: 3 | N36: =C36 & "_" & 2910 -> 10097047_2910 | O36: =_xlfn.XLOOKUP(N36,Allocation!H:H,Allocation!C:C,0) -> 0 | P36: =M36-O36 -> 3
A37: =_xlfn.XLOOKUP(C:C,'Price List'!C:C,'Price List'!A:A) -> SAMANTHA RODRIGUES GB | B37: KIKKOMAN RETAIL | C37: 10059163 | D37: KKM SOY SHIPPER 36CT | E37: =_xlfn.XLOOKUP(C:C,'Price List'!C:C,'Price List'!K:K) -> 0 | F37: =_xlfn.XLOOKUP(C:C,'Price List'!C:C,'Price List'!E:E) -> 1 | G37: =_xlfn.XLOOKUP(C:C,'Price List'!C:C,'Price List'!F:F) -> 296 ML | H37: 2920 | I37: TOL Calgary | J37: 177BC | K37: 1100 | L37: 46199 | M37: 42 | N37: =C37 & "_" & 2910 -> 10059163_2910 | O37: =_xlfn.XLOOKUP(N37,Allocation!H:H,Allocation!C:C,0) -> 0 | P37: =M37-O37 -> 42
A38: =_xlfn.XLOOKUP(C:C,'Price List'!C:C,'Price List'!A:A) -> TRACEY LAWRENCE | B38: KETTLE CHIPS | C38: 10066217 | D38: KC SEA SALT 56G GF | E38: =_xlfn.XLOOKUP(C:C,'Price List'!C:C,'Price List'!K:K) -> 0 | F38: =_xlfn.XLOOKUP(C:C,'Price List'!C:C,'Price List'!E:E) -> 24 | G38: =_xlfn.XLOOKUP(C:C,'Price List'!C:C,'Price List'!F:F) -> 56 GR | H38: 2920 | I38: TOL Calgary | J38: 27JUN2026 | K38: 1100 | L38: 46200 | M38: 5 | N38: =C38 & "_" & 2910 -> 10066217_2910 | O38: =_xlfn.XLOOKUP(N38,Allocation!H:H,Allocation!C:C,0) -> 0 | P38: =M38-O38 -> 5
A39: =_xlfn.XLOOKUP(C:C,'Price List'!C:C,'Price List'!A:A) -> MICHELLE JEWELL NT | B39: SCHAR | C39: 10038132 | D39: SCHAR BREAD A B 10GRN 8PK GF | E39: =_xlfn.XLOOKUP(C:C,'Price List'!C:C,'Price List'!K:K) -> 0 | F39: =_xlfn.XLOOKUP(C:C,'Price List'!C:C,'Price List'!E:E) -> 8 | G39: =_xlfn.XLOOKUP(C:C,'Price List'!C:C,'Price List'!F:F) -> 400 GR | H39: 2920 | I39: TOL Calgary | J39: 06272026A | K39: 1100 | L39: 46200 | M39: 162 | N39: =C39 & "_" & 2910 -> 10038132_2910 | O39: =_xlfn.XLOOKUP(N39,Allocation!H:H,Allocation!C:C,0) -> 0 | P39: =M39-O39 -> 162
A40: =_xlfn.XLOOKUP(C:C,'Price List'!C:C,'Price List'!A:A) -> SERENA LEE PR | B40: AGROPUR | C40: 10100360 | D40: CASHEL BLUE 2X1.5KG | E40: KG | F40: =_xlfn.XLOOKUP(C:C,'Price List'!C:C,'Price List'!E:E) -> 2 | G40: =_xlfn.XLOOKUP(C:C,'Price List'!C:C,'Price List'!F:F) -> 1.5 KG | H40: 2920 | I40: TOL Calgary | J40: 25510502 | K40: 1100 | L40: 46201 | M40: 3 | N40: =C40 & "_" & 2910 -> 10100360_2910 | O40: =_xlfn.XLOOKUP(N40,Allocation!H:H,Allocation!C:C,0) -> 0 | P40: =M40-O40 -> 3
A41: =_xlfn.XLOOKUP(C:C,'Price List'!C:C,'Price List'!A:A) -> NANCY QUISPE PT | B41: SHARWOODS | C41: 10050282 | D41: SHARWOODS BUTTERCHICK LITE | E41: =_xlfn.XLOOKUP(C:C,'Price List'!C:C,'Price List'!K:K) -> 0 | F41: =_xlfn.XLOOKUP(C:C,'Price List'!C:C,'Price List'!E:E) -> 6 | G41: =_xlfn.XLOOKUP(C:C,'Price List'!C:C,'Price List'!F:F) -> 395 ML | H41: 2920 | I41: TOL Calgary | J41: 103965 | K41: 1100 | L41: 46201 | M41: 1 | N41: =C41 & "_" & 2910 -> 10050282_2910 | O41: =_xlfn.XLOOKUP(N41,Allocation!H:H,Allocation!C:C,0) -> 0 | P41: =M41-O41 -> 1
A42: =_xlfn.XLOOKUP(C:C,'Price List'!C:C,'Price List'!A:A) -> Michael Gambino PR | B42: PARMELA CREAMERY | C42: 10045482 | D42: PC SHREDDED MOZZARELLA STYLE | E42: =_xlfn.XLOOKUP(C:C,'Price List'!C:C,'Price List'!K:K) -> 0 | F42: =_xlfn.XLOOKUP(C:C,'Price List'!C:C,'Price List'!E:E) -> 8 | G42: =_xlfn.XLOOKUP(C:C,'Price List'!C:C,'Price List'!F:F) -> 198 GR | H42: 2920 | I42: TOL Calgary | J42: 0062603117 | K42: 1100 | L42: 46202 | M42: 16 | N42: =C42 & "_" & 2910 -> 10045482_2910 | O42: =_xlfn.XLOOKUP(N42,Allocation!H:H,Allocation!C:C,0) -> 0 | P42: =M42-O42 -> 16
A43: =_xlfn.XLOOKUP(C:C,'Price List'!C:C,'Price List'!A:A) -> ANABELA NEVES PR | B43: DEVON CREAM COMPANY | C43: 10018980 | D43: DC CLOTTED CREAM 12X170G | E43: =_xlfn.XLOOKUP(C:C,'Price List'!C:C,'Price List'!K:K) -> 0 | F43: =_xlfn.XLOOKUP(C:C,'Price List'!C:C,'Price List'!E:E) -> 12 | G43: =_xlfn.XLOOKUP(C:C,'Price List'!C:C,'Price List'!F:F) -> 170 GR | H43: 2920 | I43: TOL Calgary | J43: 50186 | K43: 1100 | L43: 46203 | M43: 250 | N43: =C43 & "_" & 2910 -> 10018980_2910 | O43: =_xlfn.XLOOKUP(N43,Allocation!H:H,Allocation!C:C,0) -> 0 | P43: =M43-O43 -> 250
A44: =_xlfn.XLOOKUP(C:C,'Price List'!C:C,'Price List'!A:A) -> ANABELA NEVES PR | B44: DEVON CREAM COMPANY | C44: 10018980 | D44: DC CLOTTED CREAM 12X170G | E44: =_xlfn.XLOOKUP(C:C,'Price List'!C:C,'Price List'!K:K) -> 0 | F44: =_xlfn.XLOOKUP(C:C,'Price List'!C:C,'Price List'!E:E) -> 12 | G44: =_xlfn.XLOOKUP(C:C,'Price List'!C:C,'Price List'!F:F) -> 170 GR | H44: 2920 | I44: TOL Calgary | J44: 50187 | K44: 1100 | L44: 46203 | M44: 260 | N44: =C44 & "_" & 2910 -> 10018980_2910 | O44: =_xlfn.XLOOKUP(N44,Allocation!H:H,Allocation!C:C,0) -> 0 | P44: =M44-O44 -> 260
A45: =_xlfn.XLOOKUP(C:C,'Price List'!C:C,'Price List'!A:A) -> ANABELA NEVES PR | B45: DEVON CREAM COMPANY | C45: 10018980 | D45: DC CLOTTED CREAM 12X170G | E45: =_xlfn.XLOOKUP(C:C,'Price List'!C:C,'Price List'!K:K) -> 0 | F45: =_xlfn.XLOOKUP(C:C,'Price List'!C:C,'Price List'!E:E) -> 12 | G45: =_xlfn.XLOOKUP(C:C,'Price List'!C:C,'Price List'!F:F) -> 170 GR | H45: 2920 | I45: TOL Calgary | J45: 50508 | K45: 1100 | L45: 46203 | M45: 208 | N45: =C45 & "_" & 2910 -> 10018980_2910 | O45: =_xlfn.XLOOKUP(N45,Allocation!H:H,Allocation!C:C,0) -> 0 | P45: =M45-O45 -> 208
A46: =_xlfn.XLOOKUP(C:C,'Price List'!C:C,'Price List'!A:A) -> ANABELA NEVES PR | B46: DEVON CREAM COMPANY | C46: 10019099 | D46: DC DOUBLE DEVON CREAM 12X170G | E46: =_xlfn.XLOOKUP(C:C,'Price List'!C:C,'Price List'!K:K) -> 0 | F46: =_xlfn.XLOOKUP(C:C,'Price List'!C:C,'Price List'!E:E) -> 12 | G46: =_xlfn.XLOOKUP(C:C,'Price List'!C:C,'Price List'!F:F) -> 170 GR | H46: 2920 | I46: TOL Calgary | J46: 44425 | K46: 1100 | L46: 46203 | M46: 44 | N46: =C46 & "_" & 2910 -> 10019099_2910 | O46: =_xlfn.XLOOKUP(N46,Allocation!H:H,Allocation!C:C,0) -> 0 | P46: =M46-O46 -> 44
A47: =_xlfn.XLOOKUP(C:C,'Price List'!C:C,'Price List'!A:A) -> ANABELA NEVES PR | B47: DEVON CREAM COMPANY | C47: 10019099 | D47: DC DOUBLE DEVON CREAM 12X170G | E47: =_xlfn.XLOOKUP(C:C,'Price List'!C:C,'Price List'!K:K) -> 0 | F47: =_xlfn.XLOOKUP(C:C,'Price List'!C:C,'Price List'!E:E) -> 12 | G47: =_xlfn.XLOOKUP(C:C,'Price List'!C:C,'Price List'!F:F) -> 170 GR | H47: 2920 | I47: TOL Calgary | J47: 45908 | K47: 1100 | L47: 46203 | M47: 101 | N47: =C47 & "_" & 2910 -> 10019099_2910 | O47: =_xlfn.XLOOKUP(N47,Allocation!H:H,Allocation!C:C,0) -> 0 | P47: =M47-O47 -> 101
A48: =_xlfn.XLOOKUP(C:C,'Price List'!C:C,'Price List'!A:A) -> ANABELA NEVES PR | B48: DEVON CREAM COMPANY | C48: 10019099 | D48: DC DOUBLE DEVON CREAM 12X170G | E48: =_xlfn.XLOOKUP(C:C,'Price List'!C:C,'Price List'!K:K) -> 0 | F48: =_xlfn.XLOOKUP(C:C,'Price List'!C:C,'Price List'!E:E) -> 12 | G48: =_xlfn.XLOOKUP(C:C,'Price List'!C:C,'Price List'!F:F) -> 170 GR | H48: 2920 | I48: TOL Calgary | J48: 46147 | K48: 1100 | L48: 46203 | M48: 39 | N48: =C48 & "_" & 2910 -> 10019099_2910 | O48: =_xlfn.XLOOKUP(N48,Allocation!H:H,Allocation!C:C,0) -> 0 | P48: =M48-O48 -> 39
A49: =_xlfn.XLOOKUP(C:C,'Price List'!C:C,'Price List'!A:A) -> ANABELA NEVES PR | B49: DEVON CREAM COMPANY | C49: 10019099 | D49: DC DOUBLE DEVON CREAM 12X170G | E49: =_xlfn.XLOOKUP(C:C,'Price List'!C:C,'Price List'!K:K) -> 0 | F49: =_xlfn.XLOOKUP(C:C,'Price List'!C:C,'Price List'!E:E) -> 12 | G49: =_xlfn.XLOOKUP(C:C,'Price List'!C:C,'Price List'!F:F) -> 170 GR | H49: 2920 | I49: TOL Calgary | J49: 46623 | K49: 1100 | L49: 46203 | M49: 1 | N49: =C49 & "_" & 2910 -> 10019099_2910 | O49: =_xlfn.XLOOKUP(N49,Allocation!H:H,Allocation!C:C,0) -> 0 | P49: =M49-O49 -> 1
A50: =_xlfn.XLOOKUP(C:C,'Price List'!C:C,'Price List'!A:A) -> ANABELA NEVES PR | B50: DEVON CREAM COMPANY | C50: 10019099 | D50: DC DOUBLE DEVON CREAM 12X170G | E50: =_xlfn.XLOOKUP(C:C,'Price List'!C:C,'Price List'!K:K) -> 0 | F50: =_xlfn.XLOOKUP(C:C,'Price List'!C:C,'Price List'!E:E) -> 12 | G50: =_xlfn.XLOOKUP(C:C,'Price List'!C:C,'Price List'!F:F) -> 170 GR | H50: 2920 | I50: TOL Calgary | J50: 47397 | K50: 1100 | L50: 46203 | M50: 305 | N50: =C50 & "_" & 2910 -> 10019099_2910 | O50: =_xlfn.XLOOKUP(N50,Allocation!H:H,Allocation!C:C,0) -> 0 | P50: =M50-O50 -> 305
A51: =_xlfn.XLOOKUP(C:C,'Price List'!C:C,'Price List'!A:A) -> SANDRA GAGANIARAS GB | B51: FEVER TREE | C51: 10080616 | D51: FT REFRESH LIGHT TONIC 4X200 | E51: =_xlfn.XLOOKUP(C:C,'Price List'!C:C,'Price List'!K:K) -> 0 | F51: =_xlfn.XLOOKUP(C:C,'Price List'!C:C,'Price List'!E:E) -> 6 | G51: =_xlfn.XLOOKUP(C:C,'Price List'!C:C,'Price List'!F:F) -> 4X200 ML | H51: 2920 | I51: TOL Calgary | J51: 028899T1 | K51: 1100 | L51: 46203 | M51: 11 | N51: =C51 & "_" & 2910 -> 10080616_2910 | O51: =_xlfn.XLOOKUP(N51,Allocation!H:H,Allocation!C:C,0) -> 0 | P51: =M51-O51 -> 11
A52: =_xlfn.XLOOKUP(C:C,'Price List'!C:C,'Price List'!A:A) -> NANCY QUISPE PT | B52: JARRITOS | C52: 10004452 | D52: JARRITOS GRAPEFRUIT 4 PACK | E52: =_xlfn.XLOOKUP(C:C,'Price List'!C:C,'Price List'!K:K) -> 0 | F52: =_xlfn.XLOOKUP(C:C,'Price List'!C:C,'Price List'!E:E) -> 6 | G52: =_xlfn.XLOOKUP(C:C,'Price List'!C:C,'Price List'!F:F) -> 4X370 ML | H52: 2920 | I52: TOL Calgary | J52: 062025 | K52: 1100 | L52: 46203 | M52: 1 | N52: =C52 & "_" & 2910 -> 10004452_2910 | O52: =_xlfn.XLOOKUP(N52,Allocation!H:H,Allocation!C:C,0) -> 0 | P52: =M52-O52 -> 1
... A59: =_xlfn.XLOOKUP(C:C,'Price List'!C:C,'Price List'!A:A) -> TRACEY LAWRENCE | B59: SNYDERS-MAINSTREAM | C59: 10018676 | D59: SOH SHIPPER PRETZL PCS 60CT | E59: =_xlfn.XLOOKUP(C:C,'Price List'!C:C,'Price List'!K:K) -> 0 | F59: =_xlfn.XLOOKUP(C:C,'Price List'!C:C,'Price List'!E:E) -> 60 | G59: =_xlfn.XLOOKUP(C:C,'Price List'!C:C,'Price List'!F:F) -> SHIPPER | H59: 2920 | I59: TOL Calgary | J59: 04JUL2026 | K59: 1100 | L59: 46207 | M59: 1 | N59: =C59 & "_" & 2910 -> 10018676_2910 | O59: =_xlfn.XLOOKUP(N59,Allocation!H:H,Allocation!C:C,0) -> 0 | P59: =M59-O59 -> 1
A60: =_xlfn.XLOOKUP(C:C,'Price List'!C:C,'Price List'!A:A) -> ANABELA NEVES PR | B60: ILCHESTER | C60: 10013105 | D60: IL APPLEWD SMKD CHED BULK 2X3KG | E60: KG | F60: =_xlfn.XLOOKUP(C:C,'Price List'!C:C,'Price List'!E:E) -> 2 | G60: =_xlfn.XLOOKUP(C:C,'Price List'!C:C,'Price List'!F:F) -> 3 KG | H60: 2920 | I60: TOL Calgary | J60: 5252 | K60: 1100 | L60: 46209 | M60: 4 | N60: =C60 & "_" & 2910 -> 10013105_2910 | O60: =_xlfn.XLOOKUP(N60,Allocation!H:H,Allocation!C:C,0) -> 0 | P60: =M60-O60 -> 4
A61: =_xlfn.XLOOKUP(C:C,'Price List'!C:C,'Price List'!A:A) -> MICHELLE JEWELL NT | B61: SCHAR | C61: 10038130 | D61: SCHAR CRACKERS MULTIGRAIN GF | E61: =_xlfn.XLOOKUP(C:C,'Price List'!C:C,'Price List'!K:K) -> 0 | F61: =_xlfn.XLOOKUP(C:C,'Price List'!C:C,'Price List'!E:E) -> 5 | G61: =_xlfn.XLOOKUP(C:C,'Price List'!C:C,'Price List'!F:F) -> 210 GR | H61: 2920 | I61: TOL Calgary | J61: 060726D | K61: 1100 | L61: 46209 | M61: 21 | N61: =C61 & "_" & 2910 -> 10038130_2910 | O61: =_xlfn.XLOOKUP(N61,Allocation!H:H,Allocation!C:C,0) -> 0 | P61: =M61-O61 -> 21
A62: =_xlfn.XLOOKUP(C:C,'Price List'!C:C,'Price List'!A:A) -> MICHELLE JEWELL NT | B62: BOBS RED MILL | C62: 10060595 | D62: BRM GRANOLA GF LEMON BLUBRRY | E62: =_xlfn.XLOOKUP(C:C,'Price List'!C:C,'Price List'!K:K) -> 0 | F62: =_xlfn.XLOOKUP(C:C,'Price List'!C:C,'Price List'!E:E) -> 6 | G62: =_xlfn.XLOOKUP(C:C,'Price List'!C:C,'Price List'!F:F) -> 312 GR | H62: 2920 | I62: TOL Calgary | J62: 5188SCC002 | K62: 1100 | L62: 46210 | M62: 1 | N62: =C62 & "_" & 2910 -> 10060595_2910 | O62: =_xlfn.XLOOKUP(N62,Allocation!H:H,Allocation!C:C,0) -> 0 | P62: =M62-O62 -> 1
A63: =_xlfn.XLOOKUP(C:C,'Price List'!C:C,'Price List'!A:A) -> SAMANTHA RODRIGUES GB | B63: KIKKOMAN FOOD SERVIC | C63: 10059179 | D63: KKM TEMPURA BATTER 2.27KG | E63: =_xlfn.XLOOKUP(C:C,'Price List'!C:C,'Price List'!K:K) -> 0 | F63: =_xlfn.XLOOKUP(C:C,'Price List'!C:C,'Price List'!E:E) -> 6 | G63: =_xlfn.XLOOKUP(C:C,'Price List'!C:C,'Price List'!F:F) -> 2.27 KG | H63: 2920 | I63: TOL Calgary | J63: 2026JUL07 | K63: 1100 | L63: 46210 | M63: 31 | N63: =C63 & "_" & 2910 -> 10059179_2910 | O63: =_xlfn.XLOOKUP(N63,Allocation!H:H,Allocation!C:C,0) -> 0 | P63: =M63-O63 -> 31
A64: =_xlfn.XLOOKUP(C:C,'Price List'!C:C,'Price List'!A:A) -> JAMES TYSON | B64: NUPASTA INC. | C64: 10050197 | D64: NUPST GF KNJC RISONI | E64: =_xlfn.XLOOKUP(C:C,'Price List'!C:C,'Price List'!K:K) -> 0 | F64: =_xlfn.XLOOKUP(C:C,'Price List'!C:C,'Price List'!E:E) -> 8 | G64: =_xlfn.XLOOKUP(C:C,'Price List'!C:C,'Price List'!F:F) -> 210 GR | H64: 2920 | I64: TOL Calgary | J64: GEXXLP1601 | K64: 1100 | L64: 46211 | M64: 3 | N64: =C64 & "_" & 2910 -> 10050197_2910 | O64: =_xlfn.XLOOKUP(N64,Allocation!H:H,Allocation!C:C,0) -> 0 | P64: =M64-O64 -> 3
A65: =_xlfn.XLOOKUP(C:C,'Price List'!C:C,'Price List'!A:A) -> TRACEY LAWRENCE | B65: CAPE COD POTATO CHIP | C65: 10063102 | D65: CAPE CHIPS SALT LS FAT 220G | E65: =_xlfn.XLOOKUP(C:C,'Price List'!C:C,'Price List'!K:K) -> 0 | F65: =_xlfn.XLOOKUP(C:C,'Price List'!C:C,'Price List'!E:E) -> 12 | G65: =_xlfn.XLOOKUP(C:C,'Price List'!C:C,'Price List'!F:F) -> 220 GR | H65: 2920 | I65: TOL Calgary | J65: 1004857218 | K65: 1100 | L65: 46214 | M65: 9 | N65: =C65 & "_" & 2910 -> 10063102_2910 | O65: =_xlfn.XLOOKUP(N65,Allocation!H:H,Allocation!C:C,0) -> 39 | P65: =M65-O65 -> -30
A66: =_xlfn.XLOOKUP(C:C,'Price List'!C:C,'Price List'!A:A) -> TRACEY LAWRENCE | B66: CAPE COD POTATO CHIP | C66: 10063102 | D66: CAPE CHIPS SALT LS FAT 220G | E66: =_xlfn.XLOOKUP(C:C,'Price List'!C:C,'Price List'!K:K) -> 0 | F66: =_xlfn.XLOOKUP(C:C,'Price List'!C:C,'Price List'!E:E) -> 12 | G66: =_xlfn.XLOOKUP(C:C,'Price List'!C:C,'Price List'!F:F) -> 220 GR | H66: 2920 | I66: TOL Calgary | J66: HA010538 | K66: 1100 | L66: 46214 | M66: 30 | N66: =C66 & "_" & 2910 -> 10063102_2910 | O66: =_xlfn.XLOOKUP(N66,Allocation!H:H,Allocation!C:C,0) -> 39 | P66: =M66-O66 -> -9
A67: =_xlfn.XLOOKUP(C:C,'Price List'!C:C,'Price List'!A:A) -> SAMANTHA RODRIGUES GB | B67: MCVITIES | C67: 10083462 | D67: MCV DIGESTIVE DK CHOC 18592 | E67: =_xlfn.XLOOKUP(C:C,'Price List'!C:C,'Price List'!K:K) -> 0 | F67: =_xlfn.XLOOKUP(C:C,'Price List'!C:C,'Price List'!E:E) -> 12 | G67: =_xlfn.XLOOKUP(C:C,'Price List'!C:C,'Price List'!F:F) -> 300 GR | H67: 2920 | I67: TOL Calgary | J67: 20260711 | K67: 1100 | L67: 46214 | M67: 92 | N67: =C67 & "_" & 2910 -> 10083462_2910 | O67: =_xlfn.XLOOKUP(N67,Allocation!H:H,Allocation!C:C,0) -> 72 | P67: =M67-O67 -> 20
A68: =_xlfn.XLOOKUP(C:C,'Price List'!C:C,'Price List'!A:A) -> MICHELLE JEWELL NT | B68: SCHAR | C68: 10038132 | D68: SCHAR BREAD A B 10GRN 8PK GF | E68: =_xlfn.XLOOKUP(C:C,'Price List'!C:C,'Price List'!K:K) -> 0 | F68: =_xlfn.XLOOKUP(C:C,'Price List'!C:C,'Price List'!E:E) -> 8 | G68: =_xlfn.XLOOKUP(C:C,'Price List'!C:C,'Price List'!F:F) -> 400 GR | H68: 2920 | I68: TOL Calgary | J68: 07112026A | K68: 1100 | L68: 46214 | M68: 12 | N68: =C68 & "_" & 2910 -> 10038132_2910 | O68: =_xlfn.XLOOKUP(N68,Allocation!H:H,Allocation!C:C,0) -> 0 | P68: =M68-O68 -> 12
A69: =_xlfn.XLOOKUP(C:C,'Price List'!C:C,'Price List'!A:A) -> TRACEY LAWRENCE | B69: SNYDERS-MAINSTREAM | C69: 10018658 | D69: SOH PRETZEL PIECE SLT CARAML | E69: =_xlfn.XLOOKUP(C:C,'Price List'!C:C,'Price List'!K:K) -> 0 | F69: =_xlfn.XLOOKUP(C:C,'Price List'!C:C,'Price List'!E:E) -> 12 | G69: =_xlfn.XLOOKUP(C:C,'Price List'!C:C,'Price List'!F:F) -> 240 GR | H69: 2920 | I69: TOL Calgary | J69: 11JUL2026 | K69: 1100 | L69: 46214 | M69: 56 | N69: =C69 & "_" & 2910 -> 10018658_2910 | O69: =_xlfn.XLOOKUP(N69,Allocation!H:H,Allocation!C:C,0) -> 0 | P69: =M69-O69 -> 56
A70: =_xlfn.XLOOKUP(C:C,'Price List'!C:C,'Price List'!A:A) -> ANABELA NEVES PR | B70: COOMBE C BRIT PPK | C70: 10016044 | D70: CC CHED W HORSERADISH 12X150G | E70: =_xlfn.XLOOKUP(C:C,'Price List'!C:C,'Price List'!K:K) -> 0 | F70: =_xlfn.XLOOKUP(C:C,'Price List'!C:C,'Price List'!E:E) -> 12 | G70: =_xlfn.XLOOKUP(C:C,'Price List'!C:C,'Price List'!F:F) -> 150 GR | H70: 2920 | I70: TOL Calgary | J70: 304850 | K70: 1100 | L70: 46218 | M70: 4 | N70: =C70 & "_" & 2910 -> 10016044_2910 | O70: =_xlfn.XLOOKUP(N70,Allocation!H:H,Allocation!C:C,0) -> 0 | P70: =M70-O70 -> 4
A71: =_xlfn.XLOOKUP(C:C,'Price List'!C:C,'Price List'!A:A) -> MICHELLE JEWELL NT | B71: SCHAR | C71: 10038126 | D71: SCHAR BREAD DELI SEEDED GF | E71: =_xlfn.XLOOKUP(C:C,'Price List'!C:C,'Price List'!K:K) -> 0 | F71: =_xlfn.XLOOKUP(C:C,'Price List'!C:C,'Price List'!E:E) -> 5 | G71: =_xlfn.XLOOKUP(C:C,'Price List'!C:C,'Price List'!F:F) -> 250 GR | H71: 2920 | I71: TOL Calgary | J71: 260715A | K71: 1100 | L71: 46218 | M71: 10 | N71: =C71 & "_" & 2910 -> 10038126_2910 | O71: =_xlfn.XLOOKUP(N71,Allocation!H:H,Allocation!C:C,0) -> 0 | P71: =M71-O71 -> 10
A72: =_xlfn.XLOOKUP(C:C,'Price List'!C:C,'Price List'!A:A) -> AMOL PRAKASH | B72: NATURA FOODS | C72: 10003061 | D72: NATUR-A MINI SOY VANILLA ORG | E72: =_xlfn.XLOOKUP(C:C,'Price List'!C:C,'Price List'!K:K) -> 0 | F72: =_xlfn.XLOOKUP(C:C,'Price List'!C:C,'Price List'!E:E) -> 8 | G72: =_xlfn.XLOOKUP(C:C,'Price List'!C:C,'Price List'!F:F) -> 3X200 ML | H72: 2920 | I72: TOL Calgary | J72: 510659011 | K72: 1100 | L72: 46219 | M72: 62 | N72: =C72 & "_" & 2910 -> 10003061_2910 | O72: =_xlfn.XLOOKUP(N72,Allocation!H:H,Allocation!C:C,0) -> 0 | P72: =M72-O72 -> 62
... A78: =_xlfn.XLOOKUP(C:C,'Price List'!C:C,'Price List'!A:A) -> ANNA MARIA D'ANGELA | B78: PAESE MIO | C78: 10040699 | D78: PMO-OI OIL OLIVE EXTRA VIR | E78: =_xlfn.XLOOKUP(C:C,'Price List'!C:C,'Price List'!K:K) -> 0 | F78: =_xlfn.XLOOKUP(C:C,'Price List'!C:C,'Price List'!E:E) -> 12 | G78: =_xlfn.XLOOKUP(C:C,'Price List'!C:C,'Price List'!F:F) -> 750 ML | H78: 2920 | I78: TOL Calgary | J78: L2401285 | K78: 1100 | L78: 46220 | M78: 1 | N78: =C78 & "_" & 2910 -> 10040699_2910 | O78: =_xlfn.XLOOKUP(N78,Allocation!H:H,Allocation!C:C,0) -> 23 | P78: =M78-O78 -> -22
A79: =_xlfn.XLOOKUP(C:C,'Price List'!C:C,'Price List'!A:A) -> AMOL PRAKASH | B79: KINNIKINNICK | C79: 10076880 | D79: KKF FZN BREAD WHITE | E79: =_xlfn.XLOOKUP(C:C,'Price List'!C:C,'Price List'!K:K) -> 0 | F79: =_xlfn.XLOOKUP(C:C,'Price List'!C:C,'Price List'!E:E) -> 6 | G79: =_xlfn.XLOOKUP(C:C,'Price List'!C:C,'Price List'!F:F) -> 454 GR | H79: 2910 | I79: TOL Mississauga | J79: 2026JL20 | K79: 1100 | L79: 46223 | M79: 70 | N79: =C79 & "_" & 2910 -> 10076880_2910 | O79: =_xlfn.XLOOKUP(N79,Allocation!H:H,Allocation!B:B,0) -> 70
A80: =_xlfn.XLOOKUP(C:C,'Price List'!C:C,'Price List'!A:A) -> JAMES TYSON | B80: LUNDBERG RICE | C80: 10007849 | D80: LR RICE BROWN SHRT GRAIN ORG | E80: =_xlfn.XLOOKUP(C:C,'Price List'!C:C,'Price List'!K:K) -> 0 | F80: =_xlfn.XLOOKUP(C:C,'Price List'!C:C,'Price List'!E:E) -> 6 | G80: =_xlfn.XLOOKUP(C:C,'Price List'!C:C,'Price List'!F:F) -> 907 GR | H80: 2920 | I80: TOL Calgary | J80: 250721 | K80: 1100 | L80: 46224 | M80: 1 | N80: =C80 & "_" & 2910 -> 10007849_2910 | O80: =_xlfn.XLOOKUP(N80,Allocation!H:H,Allocation!C:C,0) -> 1 | P80: =M80-O80 -> 0
A81: =_xlfn.XLOOKUP(C:C,'Price List'!C:C,'Price List'!A:A) -> SAMANTHA RODRIGUES GB | B81: KIKKOMAN RETAIL | C81: 10066077 | D81: KKM SESAME OIL 148ML | E81: =_xlfn.XLOOKUP(C:C,'Price List'!C:C,'Price List'!K:K) -> 0 | F81: =_xlfn.XLOOKUP(C:C,'Price List'!C:C,'Price List'!E:E) -> 12 | G81: =_xlfn.XLOOKUP(C:C,'Price List'!C:C,'Price List'!F:F) -> 148 ML | H81: 2920 | I81: TOL Calgary | J81: 22JUL26 | K81: 1100 | L81: 46225 | M81: 2 | N81: =C81 & "_" & 2910 -> 10066077_2910 | O81: =_xlfn.XLOOKUP(N81,Allocation!H:H,Allocation!C:C,0) -> 0 | P81: =M81-O81 -> 2
A82: =_xlfn.XLOOKUP(C:C,'Price List'!C:C,'Price List'!A:A) -> ASIF AHMAD GB | B82: BLUE DIAMOND BEVERAG | C82: 10016403 | D82: BD ALM BREEZE UNSWTND ORIG | E82: =_xlfn.XLOOKUP(C:C,'Price List'!C:C,'Price List'!K:K) -> 0 | F82: =_xlfn.XLOOKUP(C:C,'Price List'!C:C,'Price List'!E:E) -> 12 | G82: =_xlfn.XLOOKUP(C:C,'Price List'!C:C,'Price List'!F:F) -> 946 ML | H82: 2920 | I82: TOL Calgary | J82: 11825207 | K82: 1100 | L82: 46229 | M82: 7 | N82: =C82 & "_" & 2910 -> 10016403_2910 | O82: =_xlfn.XLOOKUP(N82,Allocation!H:H,Allocation!C:C,0) -> 0 | P82: =M82-O82 -> 7
A83: =_xlfn.XLOOKUP(C:C,'Price List'!C:C,'Price List'!A:A) -> SAMANTHA RODRIGUES GB | B83: KIKKOMAN FOOD SERVIC | C83: 10059179 | D83: KKM TEMPURA BATTER 2.27KG | E83: =_xlfn.XLOOKUP(C:C,'Price List'!C:C,'Price List'!K:K) -> 0 | F83: =_xlfn.XLOOKUP(C:C,'Price List'!C:C,'Price List'!E:E) -> 6 | G83: =_xlfn.XLOOKUP(C:C,'Price List'!C:C,'Price List'!F:F) -> 2.27 KG | H83: 2920 | I83: TOL Calgary | J83: 2026JUL26 | K83: 1100 | L83: 46229 | M83: 69 | N83: =C83 & "_" & 2910 -> 10059179_2910 | O83: =_xlfn.XLOOKUP(N83,Allocation!H:H,Allocation!C:C,0) -> 0 | P83: =M83-O83 -> 69
A84: =_xlfn.XLOOKUP(C:C,'Price List'!C:C,'Price List'!A:A) -> NANCY QUISPE PT | B84: COOKIN' GREENS | C84: 10070148 | D84: CG FZ MEXICAN STYL RSTD CORN | E84: =_xlfn.XLOOKUP(C:C,'Price List'!C:C,'Price List'!K:K) -> 0 | F84: =_xlfn.XLOOKUP(C:C,'Price List'!C:C,'Price List'!E:E) -> 8 | G84: =_xlfn.XLOOKUP(C:C,'Price List'!C:C,'Price List'!F:F) -> 300 GR | H84: 2935 | I84: Lineage Surrey CS | J84: 072626 | K84: 1100 | L84: 46229 | M84: 15 | N84: =C84 & "_" & 2910 -> 10070148_2910 | O84: =_xlfn.XLOOKUP(N84,Allocation!H:H,Allocation!E:E,0) -> 0 | P84: =M84-O84 -> 15
A85: =_xlfn.XLOOKUP(C:C,'Price List'!C:C,'Price List'!A:A) -> MICHELLE JEWELL NT | B85: XO BAKING | C85: 10031626 | D85: XO SB MUFFN MX SWEET CRN GF | E85: =_xlfn.XLOOKUP(C:C,'Price List'!C:C,'Price List'!K:K) -> 0 | F85: =_xlfn.XLOOKUP(C:C,'Price List'!C:C,'Price List'!E:E) -> 8 | G85: =_xlfn.XLOOKUP(C:C,'Price List'!C:C,'Price List'!F:F) -> 260 GR | H85: 2930 | I85: TOL Surrey | J85: 27JUL2026 | K85: 1100 | L85: 46230 | M85: 23 | N85: =C85 & "_" & 2910 -> 10031626_2910 | O85: =_xlfn.XLOOKUP(N85,Allocation!H:H,Allocation!E:E,0) -> 0 | P85: =M85-O85 -> 23
A86: =_xlfn.XLOOKUP(C:C,'Price List'!C:C,'Price List'!A:A) -> MICHELLE JEWELL NT | B86: XO BAKING | C86: 10031630 | D86: XO SB APPLE CRISP MIX GF | E86: =_xlfn.XLOOKUP(C:C,'Price List'!C:C,'Price List'!K:K) -> 0 | F86: =_xlfn.XLOOKUP(C:C,'Price List'!C:C,'Price List'!E:E) -> 8 | G86: =_xlfn.XLOOKUP(C:C,'Price List'!C:C,'Price List'!F:F) -> 227 GR | H86: 2930 | I86: TOL Surrey | J86: 27JUL2026 | K86: 1100 | L86: 46230 | M86: 5 | N86: =C86 & "_" & 2910 -> 10031630_2910 | O86: =_xlfn.XLOOKUP(N86,Allocation!H:H,Allocation!E:E,0) -> 0 | P86: =M86-O86 -> 5
A87: =_xlfn.XLOOKUP(C:C,'Price List'!C:C,'Price List'!A:A) -> NANCY QUISPE PT | B87: SHARWOODS | C87: 10050331 | D87: SHARWOODS KORMA SAUCE | E87: =_xlfn.XLOOKUP(C:C,'Price List'!C:C,'Price List'!K:K) -> 0 | F87: =_xlfn.XLOOKUP(C:C,'Price List'!C:C,'Price List'!E:E) -> 6 | G87: =_xlfn.XLOOKUP(C:C,'Price List'!C:C,'Price List'!F:F) -> 395 ML | H87: 2920 | I87: TOL Calgary | J87: 4205W | K87: 1100 | L87: 46231 | M87: 10 | N87: =C87 & "_" & 2910 -> 10050331_2910 | O87: =_xlfn.XLOOKUP(N87,Allocation!H:H,Allocation!C:C,0) -> 0 | P87: =M87-O87 -> 10
A88: =_xlfn.XLOOKUP(C:C,'Price List'!C:C,'Price List'!A:A) -> WARREN PARK | B88: THAI KITCHEN | C88: 10048715 | D88: THAI EVERYTHING SAUCE | E88: =_xlfn.XLOOKUP(C:C,'Price List'!C:C,'Price List'!K:K) -> 0 | F88: =_xlfn.XLOOKUP(C:C,'Price List'!C:C,'Price List'!E:E) -> 6 | G88: =_xlfn.XLOOKUP(C:C,'Price List'!C:C,'Price List'!F:F) -> 293 ML | H88: 2920 | I88: TOL Calgary | J88: JUL282026 | K88: 1100 | L88: 46231 | M88: 6 | N88: =C88 & "_" & 2910 -> 10048715_2910 | O88: =_xlfn.XLOOKUP(N88,Allocation!H:H,Allocation!C:C,0) -> 0 | P88: =M88-O88 -> 6
A89: =_xlfn.XLOOKUP(C:C,'Price List'!C:C,'Price List'!A:A) -> JAMES TYSON | B89: LUNDBERG RICE | C89: 10007843 | D89: LR RICE JASMINE BROWN ORG | E89: =_xlfn.XLOOKUP(C:C,'Price List'!C:C,'Price List'!K:K) -> 0 | F89: =_xlfn.XLOOKUP(C:C,'Price List'!C:C,'Price List'!E:E) -> 6 | G89: =_xlfn.XLOOKUP(C:C,'Price List'!C:C,'Price List'!F:F) -> 907 GR | H89: 2920 | I89: TOL Calgary | J89: 250729 | K89: 1100 | L89: 46232 | M89: 8 | N89: =C89 & "_" & 2910 -> 10007843_2910 | O89: =_xlfn.XLOOKUP(N89,Allocation!H:H,Allocation!C:C,0) -> 8 | P89: =M89-O89 -> 0
A90: =_xlfn.XLOOKUP(C:C,'Price List'!C:C,'Price List'!A:A) -> SAMANTHA RODRIGUES GB | B90: KIKKOMAN FOOD SERVIC | C90: 10059175 | D90: KKM STIR FRY SAUCE 2.2KG | E90: =_xlfn.XLOOKUP(C:C,'Price List'!C:C,'Price List'!K:K) -> 0 | F90: =_xlfn.XLOOKUP(C:C,'Price List'!C:C,'Price List'!E:E) -> 6 | G90: =_xlfn.XLOOKUP(C:C,'Price List'!C:C,'Price List'!F:F) -> 2.2 KG | H90: 2910 | I90: TOL Mississauga | J90: 211BKW | K90: 1100 | L90: 46233 | M90: 24 | N90: =C90 & "_" & 2910 -> 10059175_2910 | O90: =_xlfn.XLOOKUP(N90,Allocation!H:H,Allocation!B:B,0) -> 0
A91: =_xlfn.XLOOKUP(C:C,'Price List'!C:C,'Price List'!A:A) -> SAMANTHA RODRIGUES GB | B91: WALKERS | C91: 10076520 | D91: JW SHORTBREAD FINGERS 115 | E91: =_xlfn.XLOOKUP(C:C,'Price List'!C:C,'Price List'!K:K) -> 0 | F91: =_xlfn.XLOOKUP(C:C,'Price List'!C:C,'Price List'!E:E) -> 24 | G91: =_xlfn.XLOOKUP(C:C,'Price List'!C:C,'Price List'!F:F) -> 150 GR | H91: 2920 | I91: TOL Calgary | J91: T112 | K91: 1100 | L91: 46233 | M91: 122 | N91: =C91 & "_" & 2910 -> 10076520_2910 | O91: =_xlfn.XLOOKUP(N91,Allocation!H:H,Allocation!C:C,0) -> 122 | P91: =M91-O91 -> 0
A92: =_xlfn.XLOOKUP(C:C,'Price List'!C:C,'Price List'!A:A) -> SAMANTHA RODRIGUES GB | B92: WALKERS | C92: 10076532 | D92: JW SHORTBRD CHOCO CHIP 1149 | E92: =_xlfn.XLOOKUP(C:C,'Price List'!C:C,'Price List'!K:K) -> 0 | F92: =_xlfn.XLOOKUP(C:C,'Price List'!C:C,'Price List'!E:E) -> 12 | G92: =_xlfn.XLOOKUP(C:C,'Price List'!C:C,'Price List'!F:F) -> 125 GR | H92: 2920 | I92: TOL Calgary | J92: T101 | K92: 1100 | L92: 46233 | M92: 3 | N92: =C92 & "_" & 2910 -> 10076532_2910 | O92: =_xlfn.XLOOKUP(N92,Allocation!H:H,Allocation!C:C,0) -> 3 | P92: =M92-O92 -> 0
A93: =_xlfn.XLOOKUP(C:C,'Price List'!C:C,'Price List'!A:A) -> SAMANTHA RODRIGUES GB | B93: WALKERS | C93: 10076782 | D93: JW MINI SHRTBR STARS 1816X | E93: =_xlfn.XLOOKUP(C:C,'Price List'!C:C,'Price List'!K:K) -> 0 | F93: =_xlfn.XLOOKUP(C:C,'Price List'!C:C,'Price List'!E:E) -> 12 | G93: =_xlfn.XLOOKUP(C:C,'Price List'!C:C,'Price List'!F:F) -> 125 GR | H93: 2920 | I93: TOL Calgary | J93: T213 | K93: 1100 | L93: 46233 | M93: 20 | N93: =C93 & "_" & 2910 -> 10076782_2910 | O93: =_xlfn.XLOOKUP(N93,Allocation!H:H,Allocation!C:C,0) -> 20 | P93: =M93-O93 -> 0
A94: =_xlfn.XLOOKUP(C:C,'Price List'!C:C,'Price List'!A:A) -> ANABELA NEVES PR | B94: BOTHWELL CHEESE | C94: 10033115 | D94: BC 170G EXTRA OLD WHT CHEDD | E94: =_xlfn.XLOOKUP(C:C,'Price List'!C:C,'Price List'!K:K) -> 0 | F94: =_xlfn.XLOOKUP(C:C,'Price List'!C:C,'Price List'!E:E) -> 15 | G94: =_xlfn.XLOOKUP(C:C,'Price List'!C:C,'Price List'!F:F) -> 170 GR | H94: 2930 | I94: TOL Surrey | J94: 20251202 | K94: 1100 | L94: 46233 | M94: 1 | N94: =C94 & "_" & 2910 -> 10033115_2910 | O94: =_xlfn.XLOOKUP(N94,Allocation!H:H,Allocation!E:E,0) -> 0 | P94: =M94-O94 -> 1
A95: =_xlfn.XLOOKUP(C:C,'Price List'!C:C,'Price List'!A:A) -> ANABELA NEVES PR | B95: DEVON CREAM COMPANY | C95: 10018980 | D95: DC CLOTTED CREAM 12X170G | E95: =_xlfn.XLOOKUP(C:C,'Price List'!C:C,'Price List'!K:K) -> 0 | F95: =_xlfn.XLOOKUP(C:C,'Price List'!C:C,'Price List'!E:E) -> 12 | G95: =_xlfn.XLOOKUP(C:C,'Price List'!C:C,'Price List'!F:F) -> 170 GR | H95: 2910 | I95: TOL Mississauga | J95: 51169 | K95: 1100 | L95: 46234 | M95: 430 | N95: =C95 & "_" & 2910 -> 10018980_2910 | O95: =_xlfn.XLOOKUP(N95,Allocation!H:H,Allocation!B:B,0) -> 0
A96: =_xlfn.XLOOKUP(C:C,'Price List'!C:C,'Price List'!A:A) -> ANABELA NEVES PR | B96: DEVON CREAM COMPANY | C96: 10018980 | D96: DC CLOTTED CREAM 12X170G | E96: =_xlfn.XLOOKUP(C:C,'Price List'!C:C,'Price List'!K:K) -> 0 | F96: =_xlfn.XLOOKUP(C:C,'Price List'!C:C,'Price List'!E:E) -> 12 | G96: =_xlfn.XLOOKUP(C:C,'Price List'!C:C,'Price List'!F:F) -> 170 GR | H96: 2910 | I96: TOL Mississauga | J96: 51170 | K96: 1100 | L96: 46234 | M96: 381 | N96: =C96 & "_" & 2910 -> 10018980_2910 | O96: =_xlfn.XLOOKUP(N96,Allocation!H:H,Allocation!B:B,0) -> 0
A97: =_xlfn.XLOOKUP(C:C,'Price List'!C:C,'Price List'!A:A) -> ANABELA NEVES PR | B97: DEVON CREAM COMPANY | C97: 10018980 | D97: DC CLOTTED CREAM 12X170G | E97: =_xlfn.XLOOKUP(C:C,'Price List'!C:C,'Price List'!K:K) -> 0 | F97: =_xlfn.XLOOKUP(C:C,'Price List'!C:C,'Price List'!E:E) -> 12 | G97: =_xlfn.XLOOKUP(C:C,'Price List'!C:C,'Price List'!F:F) -> 170 GR | H97: 2910 | I97: TOL Mississauga | J97: 51575 | K97: 1100 | L97: 46234 | M97: 228 | N97: =C97 & "_" & 2910 -> 10018980_2910 | O97: =_xlfn.XLOOKUP(N97,Allocation!H:H,Allocation!B:B,0) -> 0
A98: =_xlfn.XLOOKUP(C:C,'Price List'!C:C,'Price List'!A:A) -> ANABELA NEVES PR | B98: DEVON CREAM COMPANY | C98: 10019106 | D98: DC CLOTTED CRM IRSH WHSK 12X170G | E98: =_xlfn.XLOOKUP(C:C,'Price List'!C:C,'Price List'!K:K) -> 0 | F98: =_xlfn.XLOOKUP(C:C,'Price List'!C:C,'Price List'!E:E) -> 12 | G98: =_xlfn.XLOOKUP(C:C,'Price List'!C:C,'Price List'!F:F) -> 170 GR | H98: 2910 | I98: TOL Mississauga | J98: 00025 | K98: 1100 | L98: 46234 | M98: 352 | N98: =C98 & "_" & 2910 -> 10019106_2910 | O98: =_xlfn.XLOOKUP(N98,Allocation!H:H,Allocation!B:B,0) -> 0
A99: =_xlfn.XLOOKUP(C:C,'Price List'!C:C,'Price List'!A:A) -> ANABELA NEVES PR | B99: DEVON CREAM COMPANY | C99: 10019106 | D99: DC CLOTTED CRM IRSH WHSK 12X170G | E99: =_xlfn.XLOOKUP(C:C,'Price List'!C:C,'Price List'!K:K) -> 0 | F99: =_xlfn.XLOOKUP(C:C,'Price List'!C:C,'Price List'!E:E) -> 12 | G99: =_xlfn.XLOOKUP(C:C,'Price List'!C:C,'Price List'!F:F) -> 170 GR | H99: 2920 | I99: TOL Calgary | J99: 00025 | K99: 1100 | L99: 46234 | M99: 31 | N99: =C99 & "_" & 2910 -> 10019106_2910 | O99: =_xlfn.XLOOKUP(N99,Allocation!H:H,Allocation!C:C,0) -> 0 | P99: =M99-O99 -> 31
A100: =_xlfn.XLOOKUP(C:C,'Price List'!C:C,'Price List'!A:A) -> ANABELA NEVES PR | B100: DEVON CREAM COMPANY | C100: 10019107 | D100: DC CLOTTED CRM CHERRY 12X170G | E100: =_xlfn.XLOOKUP(C:C,'Price List'!C:C,'Price List'!K:K) -> 0 | F100: =_xlfn.XLOOKUP(C:C,'Price List'!C:C,'Price List'!E:E) -> 12 | G100: =_xlfn.XLOOKUP(C:C,'Price List'!C:C,'Price List'!F:F) -> 170 GR | H100: 2920 | I100: TOL Calgary | J100: 00125 | K100: 1100 | L100: 46234 | M100: 6 | N100: =C100 & "_" & 2910 -> 10019107_2910 | O100: =_xlfn.XLOOKUP(N100,Allocation!H:H,Allocation!C:C,0) -> 0 | P100: =M100-O100 -> 6
A101: =_xlfn.XLOOKUP(C:C,'Price List'!C:C,'Price List'!A:A) -> ANABELA NEVES PR | B101: DEVON CREAM COMPANY | C101: 10019108 | D101: DC AMBIENT CLOTTED CRM 24X28G | E101: =_xlfn.XLOOKUP(C:C,'Price List'!C:C,'Price List'!K:K) -> 0 | F101: =_xlfn.XLOOKUP(C:C,'Price List'!C:C,'Price List'!E:E) -> 24 | G101: =_xlfn.XLOOKUP(C:C,'Price List'!C:C,'Price List'!F:F) -> 28 GR | H101: 2920 | I101: TOL Calgary | J101: 49875 | K101: 1100 | L101: 46234 | M101: 27 | N101: =C101 & "_" & 2910 -> 10019108_2910 | O101: =_xlfn.XLOOKUP(N101,Allocation!H:H,Allocation!C:C,0) -> 0 | P101: =M101-O101 -> 27
A102: =_xlfn.XLOOKUP(C:C,'Price List'!C:C,'Price List'!A:A) -> NANCY QUISPE PT | B102: SHARWOODS | C102: 10050324 | D102: SHARWOODS CHUTNEY MANGO FS | E102: =_xlfn.XLOOKUP(C:C,'Price List'!C:C,'Price List'!K:K) -> 0 | F102: =_xlfn.XLOOKUP(C:C,'Price List'!C:C,'Price List'!E:E) -> 2 | G102: =_xlfn.XLOOKUP(C:C,'Price List'!C:C,'Price List'!F:F) -> 2.6 KG | H102: 2920 | I102: TOL Calgary | J102: 5028 | K102: 1100 | L102: 46234 | M102: 97 | N102: =C102 & "_" & 2910 -> 10050324_2910 | O102: =_xlfn.XLOOKUP(N102,Allocation!H:H,Allocation!C:C,0) -> 10 | P102: =M102-O102 -> 87
A103: =_xlfn.XLOOKUP(C:C,'Price List'!C:C,'Price List'!A:A) -> NANCY QUISPE PT | B103: THE SPICE TAILOR | C103: 10017602 | D103: TST INDO PEANUT SATAY | E103: =_xlfn.XLOOKUP(C:C,'Price List'!C:C,'Price List'!K:K) -> 0 | F103: =_xlfn.XLOOKUP(C:C,'Price List'!C:C,'Price List'!E:E) -> 5 | G103: =_xlfn.XLOOKUP(C:C,'Price List'!C:C,'Price List'!F:F) -> 260 ML | H103: 2920 | I103: TOL Calgary | J103: 4214TT1 | K103: 1100 | L103: 46234 | M103: 2 | N103: =C103 & "_" & 2910 -> 10017602_2910 | O103: =_xlfn.XLOOKUP(N103,Allocation!H:H,Allocation!C:C,0) -> 0 | P103: =M103-O103 -> 2
A104: =_xlfn.XLOOKUP(C:C,'Price List'!C:C,'Price List'!A:A) -> NANCY QUISPE PT | B104: THE SPICE TAILOR | C104: 10017611 | D104: TST ORIG TIKKA MASALA | E104: =_xlfn.XLOOKUP(C:C,'Price List'!C:C,'Price List'!K:K) -> 0 | F104: =_xlfn.XLOOKUP(C:C,'Price List'!C:C,'Price List'!E:E) -> 5 | G104: =_xlfn.XLOOKUP(C:C,'Price List'!C:C,'Price List'!F:F) -> 285 ML | H104: 2920 | I104: TOL Calgary | J104: 4245T | K104: 1100 | L104: 46234 | M104: 76 | N104: =C104 & "_" & 2910 -> 10017611_2910 | O104: =_xlfn.XLOOKUP(N104,Allocation!H:H,Allocation!C:C,0) -> 0 | P104: =M104-O104 -> 76
A105: =_xlfn.XLOOKUP(C:C,'Price List'!C:C,'Price List'!A:A) -> ANABELA NEVES PR | B105: DEVON CREAM COMPANY | C105: 10019107 | D105: DC CLOTTED CRM CHERRY 12X170G | E105: =_xlfn.XLOOKUP(C:C,'Price List'!C:C,'Price List'!K:K) -> 0 | F105: =_xlfn.XLOOKUP(C:C,'Price List'!C:C,'Price List'!E:E) -> 12 | G105: =_xlfn.XLOOKUP(C:C,'Price List'!C:C,'Price List'!F:F) -> 170 GR | H105: 2930 | I105: TOL Surrey | J105: 00125 | K105: 1100 | L105: 46234 | M105: 1 | N105: =C105 & "_" & 2910 -> 10019107_2910 | O105: =_xlfn.XLOOKUP(N105,Allocation!H:H,Allocation!E:E,0) -> 0 | P105: =M105-O105 -> 1
A106: =_xlfn.XLOOKUP(C:C,'Price List'!C:C,'Price List'!A:A) -> SAMANTHA RODRIGUES GB | B106: MCVITIES | C106: 10083460 | D106: MCV DIGESTIVE MK CHOC 18591 | E106: =_xlfn.XLOOKUP(C:C,'Price List'!C:C,'Price List'!K:K) -> 0 | F106: =_xlfn.XLOOKUP(C:C,'Price List'!C:C,'Price List'!E:E) -> 12 | G106: =_xlfn.XLOOKUP(C:C,'Price List'!C:C,'Price List'!F:F) -> 300 GR | H106: 2920 | I106: TOL Calgary | J106: 20260801 | K106: 1100 | L106: 46235 | M106: 15 | N106: =C106 & "_" & 2910 -> 10083460_2910 | O106: =_xlfn.XLOOKUP(N106,Allocation!H:H,Allocation!C:C,0) -> 0 | P106: =M106-O106 -> 15
A107: =_xlfn.XLOOKUP(C:C,'Price List'!C:C,'Price List'!A:A) -> SERENA LEE PR | B107: AGROPUR | C107: 10019706 | D107: OKA CHEESE CLASSIQ 1X2.5KG | E107: KG | F107: =_xlfn.XLOOKUP(C:C,'Price List'!C:C,'Price List'!E:E) -> 1 | G107: =_xlfn.XLOOKUP(C:C,'Price List'!C:C,'Price List'!F:F) -> 2.5 KG | H107: 2910 | I107: TOL Mississauga | J107: 06564 | K107: 1100 | L107: 46236 | M107: 1 | N107: =C107 & "_" & 2910 -> 10019706_2910 | O107: =_xlfn.XLOOKUP(N107,Allocation!H:H,Allocation!B:B,0) -> 0
A108: =_xlfn.XLOOKUP(C:C,'Price List'!C:C,'Price List'!A:A) -> SAMANTHA RODRIGUES GB | B108: MCVITIES | C108: 40099038 | D108: MCVITIES DISPLAY SHELF | E108: =_xlfn.XLOOKUP(C:C,'Price List'!C:C,'Price List'!K:K) -> 0 | F108: =_xlfn.XLOOKUP(C:C,'Price List'!C:C,'Price List'!E:E) -> 1 | G108: =_xlfn.XLOOKUP(C:C,'Price List'!C:C,'Price List'!F:F) -> SHIPPER COMPONENT | H108: 2930 | I108: TOL Surrey | J108: 260208 | K108: 1100 | L108: 46236 | M108: 36 | N108: =C108 & "_" & 2910 -> 40099038_2910 | O108: =_xlfn.XLOOKUP(N108,Allocation!H:H,Allocation!E:E,0) -> 0 | P108: =M108-O108 -> 36
A109: =_xlfn.XLOOKUP(C:C,'Price List'!C:C,'Price List'!A:A) -> SAMANTHA RODRIGUES GB | B109: MCVITIES | C109: 40099042 | D109: MCVITIES DISPLAY SHIPPER | E109: =_xlfn.XLOOKUP(C:C,'Price List'!C:C,'Price List'!K:K) -> 0 | F109: =_xlfn.XLOOKUP(C:C,'Price List'!C:C,'Price List'!E:E) -> 1 | G109: =_xlfn.XLOOKUP(C:C,'Price List'!C:C,'Price List'!F:F) -> SHIPPER COMPONENT | H109: 2930 | I109: TOL Surrey | J109: 260208 | K109: 1100 | L109: 46236 | M109: 9 | N109: =C109 & "_" & 2910 -> 40099042_2910 | O109: =_xlfn.XLOOKUP(N109,Allocation!H:H,Allocation!E:E,0) -> 0 | P109: =M109-O109 -> 9
A110: =_xlfn.XLOOKUP(C:C,'Price List'!C:C,'Price List'!A:A) -> JAMES TYSON | B110: NUPASTA INC. | C110: 10050485 | D110: NUPST VEGAN BOLOGNESE | E110: =_xlfn.XLOOKUP(C:C,'Price List'!C:C,'Price List'!K:K) -> 0 | F110: =_xlfn.XLOOKUP(C:C,'Price List'!C:C,'Price List'!E:E) -> 6 | G110: =_xlfn.XLOOKUP(C:C,'Price List'!C:C,'Price List'!F:F) -> 310 GR | H110: 2920 | I110: TOL Calgary | J110: GEXXLT0201 | K110: 1100 | L110: 46237 | M110: 48 | N110: =C110 & "_" & 2910 -> 10050485_2910 | O110: =_xlfn.XLOOKUP(N110,Allocation!H:H,Allocation!C:C,0) -> 48 | P110: =M110-O110 -> 0
A111: =_xlfn.XLOOKUP(C:C,'Price List'!C:C,'Price List'!A:A) -> JAMES TYSON | B111: NUPASTA INC. | C111: 10050486 | D111: NUPST VEGAN CHILI | E111: =_xlfn.XLOOKUP(C:C,'Price List'!C:C,'Price List'!K:K) -> 0 | F111: =_xlfn.XLOOKUP(C:C,'Price List'!C:C,'Price List'!E:E) -> 6 | G111: =_xlfn.XLOOKUP(C:C,'Price List'!C:C,'Price List'!F:F) -> 310 GR | H111: 2920 | I111: TOL Calgary | J111: GEXXLT0801 | K111: 1100 | L111: 46237 | M111: 21 | N111: =C111 & "_" & 2910 -> 10050486_2910 | O111: =_xlfn.XLOOKUP(N111,Allocation!H:H,Allocation!C:C,0) -> 21 | P111: =M111-O111 -> 0
A112: =_xlfn.XLOOKUP(C:C,'Price List'!C:C,'Price List'!A:A) -> ASIF AHMAD GB | B112: BLUE DIAMOND BEVERAG | C112: 10016408 | D112: BD ALM BREEZE BARISTA FS | E112: =_xlfn.XLOOKUP(C:C,'Price List'!C:C,'Price List'!K:K) -> 0 | F112: =_xlfn.XLOOKUP(C:C,'Price List'!C:C,'Price List'!E:E) -> 12 | G112: =_xlfn.XLOOKUP(C:C,'Price List'!C:C,'Price List'!F:F) -> 946 ML | H112: 2930 | I112: TOL Surrey | J112: 11825215J | K112: 1100 | L112: 46237 | M112: 20 | N112: =C112 & "_" & 2910 -> 10016408_2910 | O112: =_xlfn.XLOOKUP(N112,Allocation!H:H,Allocation!E:E,0) -> 0 | P112: =M112-O112 -> 20
A113: =_xlfn.XLOOKUP(C:C,'Price List'!C:C,'Price List'!A:A) -> JAMES TYSON | B113: NUPASTA INC. | C113: 10050486 | D113: NUPST VEGAN CHILI | E113: =_xlfn.XLOOKUP(C:C,'Price List'!C:C,'Price List'!K:K) -> 0 | F113: =_xlfn.XLOOKUP(C:C,'Price List'!C:C,'Price List'!E:E) -> 6 | G113: =_xlfn.XLOOKUP(C:C,'Price List'!C:C,'Price List'!F:F) -> 310 GR | H113: 2930 | I113: TOL Surrey | J113: GEXXLT0801 | K113: 1100 | L113: 46237 | M113: 20 | N113: =C113 & "_" & 2910 -> 10050486_2910 | O113: =_xlfn.XLOOKUP(N113,Allocation!H:H,Allocation!E:E,0) -> 0 | P113: =M113-O113 -> 20
A114: =_xlfn.XLOOKUP(C:C,'Price List'!C:C,'Price List'!A:A) -> MICHELLE JEWELL NT | B114: SCHAR | C114: 10038130 | D114: SCHAR CRACKERS MULTIGRAIN GF | E114: =_xlfn.XLOOKUP(C:C,'Price List'!C:C,'Price List'!K:K) -> 0 | F114: =_xlfn.XLOOKUP(C:C,'Price List'!C:C,'Price List'!E:E) -> 5 | G114: =_xlfn.XLOOKUP(C:C,'Price List'!C:C,'Price List'!F:F) -> 210 GR | H114: 2930 | I114: TOL Surrey | J114: 030826C | K114: 1100 | L114: 46237 | M114: 42 | N114: =C114 & "_" & 2910 -> 10038130_2910 | O114: =_xlfn.XLOOKUP(N114,Allocation!H:H,Allocation!E:E,0) -> 0 | P114: =M114-O114 -> 42
A115: =_xlfn.XLOOKUP(C:C,'Price List'!C:C,'Price List'!A:A) -> SERENA LEE PR | B115: AGROPUR | C115: 10100364 | D115: FRANCE BLUE | E115: =_xlfn.XLOOKUP(C:C,'Price List'!C:C,'Price List'!K:K) -> 0 | F115: =_xlfn.XLOOKUP(C:C,'Price List'!C:C,'Price List'!E:E) -> 8 | G115: =_xlfn.XLOOKUP(C:C,'Price List'!C:C,'Price List'!F:F) -> 125 GR | H115: 2910 | I115: TOL Mississauga | J115: 12612626 | K115: 1100 | L115: 46238 | M115: 4 | N115: =C115 & "_" & 2910 -> 10100364_2910 | O115: =_xlfn.XLOOKUP(N115,Allocation!H:H,Allocation!B:B,0) -> 0
A116: =_xlfn.XLOOKUP(C:C,'Price List'!C:C,'Price List'!A:A) -> ANABELA NEVES PR | B116: BELLA CAS ALBER LEAP | C116: 10100030 | D116: BCC CHEESE MINI BUFFALO BOCCONCINI | E116: =_xlfn.XLOOKUP(C:C,'Price List'!C:C,'Price List'!K:K) -> 0 | F116: =_xlfn.XLOOKUP(C:C,'Price List'!C:C,'Price List'!E:E) -> 6 | G116: =_xlfn.XLOOKUP(C:C,'Price List'!C:C,'Price List'!F:F) -> 180 GR | H116: 2910 | I116: TOL Mississauga | J116: 260625161 | K116: 1100 | L116: 46238 | M116: 1 | N116: =C116 & "_" & 2910 -> 10100030_2910 | O116: =_xlfn.XLOOKUP(N116,Allocation!H:H,Allocation!B:B,0) -> 0
A117: =_xlfn.XLOOKUP(C:C,'Price List'!C:C,'Price List'!A:A) -> JASON MULDOON PT | B117: RUSTICO DELI | C117: 10040391 | D117: RUS GENOA SALAMI HOT | E117: KG | F117: =_xlfn.XLOOKUP(C:C,'Price List'!C:C,'Price List'!E:E) -> 4 | G117: =_xlfn.XLOOKUP(C:C,'Price List'!C:C,'Price List'!F:F) -> 1.5 KG | H117: 2910 | I117: TOL Mississauga | J117: 45310 | K117: 1100 | L117: 46238 | M117: 8 | N117: =C117 & "_" & 2910 -> 10040391_2910 | O117: =_xlfn.XLOOKUP(N117,Allocation!H:H,Allocation!B:B,0) -> 0
A118: =_xlfn.XLOOKUP(C:C,'Price List'!C:C,'Price List'!A:A) -> ANABELA NEVES PR | B118: BELLA CAS ALBER LEAP | C118: 10100028 | D118: BCC CHEESE BURRATA 6x250G | E118: =_xlfn.XLOOKUP(C:C,'Price List'!C:C,'Price List'!K:K) -> 0 | F118: =_xlfn.XLOOKUP(C:C,'Price List'!C:C,'Price List'!E:E) -> 6 | G118: =_xlfn.XLOOKUP(C:C,'Price List'!C:C,'Price List'!F:F) -> 250 GR | H118: 2910 | I118: TOL Mississauga | J118: 260707172 | K118: 1100 | L118: 46240 | M118: 7 | N118: =C118 & "_" & 2910 -> 10100028_2910 | O118: =_xlfn.XLOOKUP(N118,Allocation!H:H,Allocation!B:B,0) -> 0
A119: =_xlfn.XLOOKUP(C:C,'Price List'!C:C,'Price List'!A:A) -> ANABELA NEVES PR | B119: BOTHWELL CHEESE | C119: 10033277 | D119: BC BULK SHRED JALAPENO MJ | E119: =_xlfn.XLOOKUP(C:C,'Price List'!C:C,'Price List'!K:K) -> 0 | F119: =_xlfn.XLOOKUP(C:C,'Price List'!C:C,'Price List'!E:E) -> 8 | G119: =_xlfn.XLOOKUP(C:C,'Price List'!C:C,'Price List'!F:F) -> 1 KG | H119: 2910 | I119: TOL Mississauga | J119: 20260428 | K119: 1100 | L119: 46240 | M119: 28 | N119: =C119 & "_" & 2910 -> 10033277_2910 | O119: =_xlfn.XLOOKUP(N119,Allocation!H:H,Allocation!B:B,0) -> 0
A120: =_xlfn.XLOOKUP(C:C,'Price List'!C:C,'Price List'!A:A) -> SERENA LEE PR | B120: AGROPUR | C120: 10019690 | D120: SGN SM CHEESE GOAT 180GR | E120: =_xlfn.XLOOKUP(C:C,'Price List'!C:C,'Price List'!K:K) -> 0 | F120: =_xlfn.XLOOKUP(C:C,'Price List'!C:C,'Price List'!E:E) -> 6 | G120: =_xlfn.XLOOKUP(C:C,'Price List'!C:C,'Price List'!F:F) -> 180 GR | H120: 2910 | I120: TOL Mississauga | J120: S26134 | K120: 1100 | L120: 46241 | M120: 3 | N120: =C120 & "_" & 2910 -> 10019690_2910 | O120: =_xlfn.XLOOKUP(N120,Allocation!H:H,Allocation!B:B,0) -> 0
A121: =_xlfn.XLOOKUP(C:C,'Price List'!C:C,'Price List'!A:A) -> SANDRA GAGANIARAS GB | B121: RANA RETAIL | C121: 10100310 | D121: RANA ITALIAN SAUSAGE RAVIOLI 300 GR | E121: =_xlfn.XLOOKUP(C:C,'Price List'!C:C,'Price List'!K:K) -> 0 | F121: =_xlfn.XLOOKUP(C:C,'Price List'!C:C,'Price List'!E:E) -> 6 | G121: =_xlfn.XLOOKUP(C:C,'Price List'!C:C,'Price List'!F:F) -> 300 GR | H121: 2910 | I121: TOL Mississauga | J121: 0807413914 | K121: 1100 | L121: 46241 | M121: 13 | N121: =C121 & "_" & 2910 -> 10100310_2910 | O121: =_xlfn.XLOOKUP(N121,Allocation!H:H,Allocation!B:B,0) -> 0
...
